Workbook

Sheet Концепция
A6: КОНЦЕПЦИЯ ЗА ИЗГРАЖДАНЕ НА УЧИЛИЩНА STEM СРЕДА
A7: 1 | B7: ДАННИ ЗА КОНТАКТ
A8: 1.1 | B8: Име и фамилия на директора на училището
A9: 1.2 | B9: Телефон за връзка
A10: 1.3 | B10: Име и фамилия на лице за контакт по STEM
A11: 1.4 | B11: Длъжност
A12: 1.5 | B12: Телефон за връзка
A13: 1.6 | B13: E-mail
A14: 2 | B14: ОБЩИ ДАННИ ЗА УЧИЛИЩЕТО
A15: 2.1 | B15: Код на училището по НЕИСПУО:
A16: 2.2 | B16: Код на училището по ЕИК: | F16: =IFERROR(VLOOKUP(F15, Училища!A:W, 23, FALSE()), "")
A17: 2.3 | B17: Наименование на образователна институция: | F17: =IFERROR(VLOOKUP(F15, Училища!A:W, 5, FALSE()), "")
A18: 2.4 | B18: Област: | F18: =IFERROR(VLOOKUP(F15, Училища!A:F, 2, FALSE()), "")
A19: 2.5 | B19: Община : | F19: =IFERROR(VLOOKUP(F15, Училища!A:F, 3, FALSE()), "")
A20: 2.6 | B20: Населено място: | F20: =IFERROR(VLOOKUP(F15, Училища!A:F, 4, FALSE()), "")
A21: 2.7 | B21: Вид училище: | F21: =IFERROR(VLOOKUP(F15, Училища!A:G, 7, FALSE()), "")
A22: 2.8 | B22: Детайлен вид на училище: | F22: =IFERROR(VLOOKUP(F15, Училища!A:V, 6, FALSE()), "")
A23: 2.9 | B23: Профил или професонално направление, ако има такива: | F23: Софтуерни и хардуерни науки, Чужди езици
A24: 2.1 | B24: Брой на учениците през учебната 2020-2021 г.: | F24: =IFERROR(VLOOKUP(F15, Училища!A:V, 8, FALSE()), "")
A25: 2.11 | B25: Брой на учениците през учебната 2021-2022 г.: | F25: =IFERROR(VLOOKUP(F15, Училища!A:V, 9, FALSE()), "")
A26: 2.12 | B26: Брой на учениците през учебната 2022-2023 г.: | F26: =IFERROR(VLOOKUP(F15, Училища!A:V, 10, FALSE()), "")
A27: 2.13 | B27: Средноаритметичен брой ученици за учебните 2020/2021, 2021/2022 и 2022/2023 учебна година | F27: =IFERROR(VLOOKUP(F15, Училища!A:V, 11, FALSE()), "")
A28: 2.14 | B28: Брой на педагогическия персонал за 2022-2023 г.: | F28: 85
A29: 2.15 | B29: Училището Ви има ли изграден STEM център към момента на кандидатстване? (Моля отбележете)
A31: 2.16 | B31: Вид на финансиране на училището: | F31: =IFERROR(VLOOKUP(F15, Училища!A:V, 7, FALSE()), "")
A32: 2.17 | B32: В кой/кои образователни етапи ще се използва центърът? (Можете да посочите повече от един)
A33: 2.18 | B33: Колко учители (и други специалисти) планирате да включите за работа в STEM среда в рамките на една учебна година? | F33: 6
A34: 2.19 | B34: Какъв е профилът на учителите, които планирате да бъдат включени в изграждането на STEM центъра? | F34: Учители по математика, информатика, информационни технологии, компютърно моделиране и информационни технологии
A35: 3 | B35: ВИДОВЕ РАЗХОДИ | I35: Максимален размер на средствата за изграждане на училищна STEM среда | J35: Искано финансиране за изграждане на училищна STEM среда
A36: 3.1 | B36: Средства STEM в лв. с ДДС | I36: =IFERROR(VLOOKUP(F15, Училища!A:V, 12, FALSE()), "") | J36: =J37+J38+J39+J40 -> 299575.46
A37: 3.2 | B37: в това число максимален размер на разходите за СМР и обзавеждане за STEM (до 45 % от средствата за STEM) в лв. с ДДС | I37: =IFERROR(VLOOKUP(F15, Училища!A:V, 13, FALSE()), "") | J37: =+'Направление 1'!H208+'Направление 1'!H211+'Направление 2'!H208+'Направление 2'!H211+'Направление 3'!H208+'Направление 3'!H211+'Направление 4'!H208+'Направление 4'!H211+'Направление 5'!H208+'Направление 5'!H211 -> 99126.528
A38: 3.3 | B38: в това число минимален размер на разходите за оборудване за STEM (минимум 45 % от средствата за STEM) в лв. с ДДС | I38: =IFERROR(VLOOKUP(F15, Училища!A:V, 14, FALSE()), "") | J38: =+'Направление 1'!H84++'Направление 2'!H84+'Направление 3'!H84+'Направление 4'!H84+'Направление 5'!H84 -> 170496.94
A39: 3.4 | B39: в това число максимален размер на разходите за допълнително специализирано оборудване за STEM (до 20 % от разходите за оборудване за STEM) в лв. с ДДС | I39: =IFERROR(VLOOKUP(F15, Училища!A:V, 15, FALSE()), "") | J39: =+'Специализирано оборудване'!H84 -> 0
A40: 3.5 | B40: в това число максимален размер на разходите за софтуер за STEM (до 10 % от средствата за STEM) в лв. с ДДС | I40: =IFERROR(VLOOKUP(F15, Училища!A:V, 16, FALSE()), "") | J40: =+'Направление 1'!H126+'Направление 2'!H126+'Направление 3'!H126+'Направление 4'!H126+'Направление 5'!H126+'Специализирано оборудване'!H126 -> 29952
A41: 3.6 | B41: Средства ВОСКС в лв. с ДДС | I41: =IFERROR(VLOOKUP(F15, Училища!A:V, 17, FALSE()), "") | J41: =+ВОСКС!H127 -> 59310
A42: 3.7 | B42: в това число максимален размер на разходите за софтуер за ВОСКС (до 10 % от средствата за ВОСКС) в лв. с ДДС | I42: =IFERROR(VLOOKUP(F15, Училища!A:V, 19, FALSE()), "") | J42: =+ВОСКС!H126 -> 5904
A43: 3.8 | B43: Общо средства (STEM и ВОСКС) в лв. с ДДС | I43: =IFERROR(VLOOKUP(F15, Училища!A:V, 20, FALSE()), "") | J43: =J36+J41 -> 358885.46
A44: 3.9 | B44: Средства за организация и управление (1%) от средствата за STEM и ВОСКС в лв. с ДДС | I44: =IFERROR(VLOOKUP(F15, Училища!A:V, 21, FALSE()), "") | J44: =+J43*0.01 -> 3588.8546
A45: 3.1 | B45: Общо средства за изграждане на училищна STEM среда в лв. с ДДС | I45: =IFERROR(VLOOKUP(F15, Училища!A:V, 22, FALSE()), "") | J45: =+J43+J44 -> 362474.32
A46: 4 | B46: Моля при подаване на попълнената Концепция за изграждане на училищна STEM среда да се приложат и следните задължителни документи:
A47: 4.1 | B47: Решение на Педагогическия съвет за одобряване на Концепция за изграждане на училищна STEM среда по образец (Приложение IIIb);
A48: 4.2 | B48: Декларации за информирано съгласие от поне двама педагогически специалисти за участие в реализирането на Концепция за изграждане на училищна STEM среда по образец (Приложение IIIa)
A49: 5 | B49: Декларации:
A50: 5.1 | B50: Декларирам, че данните относно училището в НЕИСПУО са коректни, пълни и актуални:
A52: 5.2 | B52: Декларирам, че в концепцията не са включени разходи, финансирани по друг проект, програма или каквато и да е друга финансова схема от общинския бюджет, националния бюджет, бюджета на Европейския съюз или друга донорска програма през последните 5 години преди крайния срок за подаване на Концепцията за изграждане на училищна STEM среда
A53: 6 | B53: КОНЦЕПЦИЯ ЗА ИЗГРАЖДАНЕ НА УЧИЛИЩНА STEM СРЕДА
A54: 6.1 | B54: Описание на идеята за изграждане на STEM среда:
B55: Учебната STEM среда на училище "Х" ще бъде съставена от 1 лаборатория в направление „Математика и информатика“ със зона "Център за дигитални създатели", съответстваща на 2 класни стаи и фоайе, с подходяща локация на 4. етаж, с иновативни архитектурни решения, които позволяват ученето да е динамично, многофункционално, да следва съвременните тенденции както за изработка на специфичната мебелировка, така и да съответства на учебното съдържание и възрастта на учениците. Преобразеното пространство ще предлага свободно движение и места за отдих, усамотяване, работа по групи, комуникация на учениците от различните класове. Предвижда се и изграждане на пространство за учителите във фоайето. Планираната зона по направление „Математика и информатика“ ще бъде интегрирана по следния начин: Технологично пространство за симулации и експерименти – включващо интерактивен дисплей, преносими компютри, 3D очила за виртуална реалност, 3D принтер, програрируем робот, прилежащо мрежово оборудване и интерактивна мултимедийна система за обучение, осигуряваща различни функционалности (вкл. за дистанционно обучение). Системата се състои от интерактивен дисплей, микрофон, видеорегистратор, камери, професионален монитор и съответен софтуер, необходим за функционирането на системата. Една от ключовите функции е мултимедийната тъч "черна дъска“, позволяваща връзка с други устройства и потребители и взаимодействие с учебното съдържание по интерактивен начин - то може да бъде споделяно и използвано от различни източници. Възможността за запис позволява на учениците да преглеждат материалите повторно и да ги използват за подготовка. Системата дава възможност за споделянето на учебни ресурси в рамките на една платформа, което ще допринесе за уеднаквяване на качеството на образованието в различните професионални области. За функционирането на системата е необходим и съответен софтуер, предлагащ разширени възможности за учебна дейност - с професионални хардуерни устройства и софтуерни инструменти, учителите и учениците в основната класна стая могат да споделят експериментите с други класни стаи в реално време и да взаимодействат помежду си. Панелът на дисплея гарантира, че основната и вторичната класна стая споделят едно и също съдържание по едно и също време. Тази интерактивност помага на всички ученици да се включат в дейности в клас и да получат незабавна обратна връзка или разяснения от учителите. Свободно пространство за дискусии, позволяващо подготовка и работа по групи. Планира се изграждане на 6 ВОСКС извън STEM лабораторията, като целта е премахване на съществуващите бариери за комуникация. Специализираната зона "Център за дигитални създатели" е подходяща за ученици в прогимназиален и гимназиален етап и позволява да учат „чрез правене“, да експериментират, да разработват нови идеи, да демонстрират и обсъждат успешните си проекти. Планираното специализирано оборудване в зоната за дигитални създатели играе ключова роля в образователния процес, като предоставя реални и практически възможности на учениците да изследват и опознават различни научни концепции и явления, което им помага да разбират заобикалящия ги свят; оборудването стимулира активното участие и инициатива. Децата имат възможност да изпълняват реални експерименти, да правят наблюдения и да изследват, което ги мотивира да проявяват своето собствено любопитство и съзнателност. Промененото учебно съдържание с фокус върху SТЕМ ще бъде насочено към следните учебни предмети: Математика, Информатика, Информационни технологии и Компютърно моделиране и информационни технологии и ще се базира на : интегрирани учебни модули, , нови модули на учебно съдържание и нови извънкласни дейности. Допълнителното оборудване кореспондира с профила на учителите - специалисти по математика, информатика и информационни технологии, които ще са свързващото звено към новото иновативно учебно пространство. Избраните учебни предмети са обвързани с конкретното оборудване, като се надгражда задължителният учебен материал с възможности за изследвания, за създаване на практически умения с примери от реалния живот и „context based“ технологично обучение. Цели се подготовка и достигане на конкурентно равнище на учениците в дигиталната ера. Ще бъдат приложени различни видове методи на оценяване, включително и на учениците със СОП, като се пристъпва към проектно-базиран и проблемно-базиран образователен процес и ще се създаде възможност за индивидуално мониториране. Процесът е интерактивен, мотивиращ ученика, с игрови елементи . Училищното ръководство не предвижда закупуването на допълнително специализирано оборудване понастоящото проектно предложение.
A56: 6.2 | B56: Обосновка на идеята за изграждане на STEM среда:
B57: Изграждането на STEM учебната среда ще доведе до създаване на нова организация на учебните и административни процеси, подкрепяща иновативните дейности. С цел ефективно използване на оборудването ръководството ще работи съвместно с учители със съответния на оборудването профил, а именно специалисти по информационни технологии, математика и информатика, компютърно моделиране. Училищният персонал е високо квалифициран и ще бъде приобщен към модерната среда с възможност за по-улеснена комуникация. Също така ще бъде приветстван и обменът на добри практики от по-опитните към по-неопитните специалисти. Проектното предложение предвижда и създаването на група от учители “лидери”, чиято цел ще бъде подкрепа и взаимодействие. Планира се “технически мениджър” да води учителите по пътя на дигиталното израстване и “специалист по учебно съдържание” да интегрира различните учебни дисциплини в единен учебен проект. Необходима е правилна организация на учебните и административни дейности, техническо подпомагане на работещите по проекта. За целта ще се създаде нова роля: техническа и дигитална подкрепа, където учители с технологичен опит ще съдействат при проблеми. Всички заинтересовани страни са силно мотивирани и вярват в необходимостта от изграждане на модерна архитектурна среда, предлагаща подходящи и иновативни образователни технологии. Лабораторният комплекс, който училището планира да изгради, е цялостно съчетание на мебелна и архитектурна среда, оборудване, софтуер, компютърна мрежа. Съществуващите класни стаи с прилежащо фоайе ще бъдат съединени в лабораторно пространство - ще бъдат извършени ремонти дейности за обединяване, освежаване, полагане на подходяща подова настилка и техническа обособеност, включваща постоянен високоскоростен интернет, достатъчен брой контакти и кабели за електричество на зоната. Дейностите не изискват разрешително за строеж и са съобразени с мерките за екологична устоучивост и не са предвидени за реализиране по други процедури на НПВУ и предишните финансирания на училището, така че да се избегне двойно финансиране по програмата. Планираният брой технологично оборудване, част от което са 28 преносими компютъра, 2 интерактивни дисплея, заедно с прилежащото мрежово оборудване и програмируемите роботи, са съобразени със специфични нужди, произтичащи от изброените вече изучавани предмети, така и с нуждите на училището за обособяване на брой учебни места - всичко това за достъп на 52 ученици в един момент. Интериорното оформление, включващо чинове и столове, учителски маси и столове, етажерки и шкафове, е така проектирано, че да предлага гъвкавост и мобилност в учебния процес – мебелите ще бъдат леки, позволяващи бърза адаптация според нуждите, възрастта на учениците, учебния предмет. По този начин ще се постигне ефективна организация и на пространствата, и на учебния процес, като се дава възможност за работа с 2 класа едновременно при нужда, за групова и индивидуална работа. С професионални хардуерни устройства и софтуерни инструменти учителите и учениците в основните и вторичните класни стаи ще могат да виждат класните стаи на другия в реално време и да взаимодействат помежду си. Панелът на дисплея гарантира, че основната и вторичната класна стая споделят едно и също съдържание по едно и също време. Тази интерактивност помага на всички ученици да се включат в дейности в клас и да получат незабавна обратна връзка или разяснения от учителите. Дигиталните и недигитални технологии ще бъдат интегрирани във физическата среда с възможност активно да се включат и ученици със СОП, ще се създаде възможност за индивидуално мониториране и на активността им. Дизайнът на учебните пространства ще позволи на учениците да бъдат групирани по алтернативни начини, съобразно на техните интереси.
A58: 6.3 | B58: Описание на мерките за осигуряване устойчивост на идеята за изграждане на STEM среда
B59: Описаното проектно предложение и планът за СМР дейности за създаване на иновативна STEM среда в училище "Х" са с нужната техническа обезпеченост, в т.ч. с поставяне на достатъчен брой контакти и кабели за електричество. В стаите е планирано създаване на условия за постоянен високоскоростен интернет, както и възможност за гъвкаво използване на специфичното оборудване. С оглед на факта, че текущата електрическа инсталация е остаряла и не е способна да поеме натоварването от новото оборудване и с цел избягване на аварии и повреда на техниката, се предвижда реновирането ѝ в рамките на бюджета за СМР дейности. Планираното за закупуване оборудване, което ще бъде инсталирано в пространството, предвидено за изграждането на STEM средата, е ново и фигурира в текущата производствена листа на производителя му, придружено с гаранционни документи и необходимите софтурени компоненти за неговото функциониране. Също така е в пълен синхрон със стандартите в Република България относно техническа експлоатация, пожаробезопасност, норми за безопасност, включване към електрическата мрежа. За да бъде осигурена максимална ефективност и управление на техническото съоръжение на новия STEM център и в същото време да се гарантира обезпечаване на образователния процес, ръководството на училище "Х" планира да осигури дългосрочен абонамент за поддръжка на оборудването. Това включва предприемане на рутинни профилактични проверки, сервизиране и обновяване на необходимите части. Редовната поддръжка гарантира, че оборудването ще работи ефективно и ефикасно в най-дълъг период от време. Също така за постигане на екологична устоичивост при евентуална повреда на дадени части се планира рециклирането или преизползването им, вместо изхвърляне. Това намалява вредното въздействие върху околната среда и допринася за устойчивостта на образователната система, като дава добър пример на учениците как могат да прилагат принципите на кръговата икономика. С оглед устойчивост на идеята са планирани активното използване на профилите на учителите в онлайн платформи, които дават възможност за заимстване на идеи и обмен на добри практики при разработване на учебните STEM уроци и работа с конкретното оборудване. Някои учебни материали и експерименти могат да бъдат представени във виртуална среда, където всички заинтересовани страни – учители и ученици, в т.ч. и от други училища ще имат достъп до тях чрез компютри или мобилни устройства. По този начин ще бъдат създадени и STEM области, което води до подобряване на образователната среда не само на локално ниво. Планира се и oрганизирането на допълнителни квалификацинни курсове на учителите, свързани с работата в лабораторията. Поради бързо и постоянно развиващия се характер на дигиталните услуги проектното предложение предвижда на всеки 12 месеца да се актуализират знаниятa и уменията на учителите в зависимост от промените в заобикалящия ни свят.
A60: 7 | B60: НАПРАВЛЕНИЯ НА STEM ЦЕНТЪРА, ВОСКС И СПЕЦИАЛИЗИРАНО ОБОРУДВАНЕ
A61: 7.1 | B61: Направление 1 „Роботика и Кибер-физични системи"
B62: Планирано за закупуване оборудване
B63: Наименование на оборудване | E63: Технически спецификации | H63: Минимално ниво на оборудване | J63: Количество
A64: 1 | B64: =IF('Направление 1'!B4="","",'Направление 1'!B4) | E64: =IF('Направление 1'!C4="","",'Направление 1'!C4) | H64: =IF('Направление 1'!D4="","",'Направление 1'!D4) | J64: =IF('Направление 1'!E4=0,"",'Направление 1'!E4)
A65: 2 | B65: =IF('Направление 1'!B5="","",'Направление 1'!B5) | E65: =IF('Направление 1'!C5="","",'Направление 1'!C5) | H65: =IF('Направление 1'!D5="","",'Направление 1'!D5) | J65: =IF('Направление 1'!E5=0,"",'Направление 1'!E5)
A66: 3 | B66: =IF('Направление 1'!B6="","",'Направление 1'!B6) | E66: =IF('Направление 1'!C6="","",'Направление 1'!C6) | H66: =IF('Направление 1'!D6="","",'Направление 1'!D6) | J66: =IF('Направление 1'!E6=0,"",'Направление 1'!E6)
A67: 4 | B67: =IF('Направление 1'!B7="","",'Направление 1'!B7) | E67: =IF('Направление 1'!C7="","",'Направление 1'!C7) | H67: =IF('Направление 1'!D7="","",'Направление 1'!D7) | J67: =IF('Направление 1'!E7=0,"",'Направление 1'!E7)
A68: 5 | B68: =IF('Направление 1'!B8="","",'Направление 1'!B8) | E68: =IF('Направление 1'!C8="","",'Направление 1'!C8) | H68: =IF('Направление 1'!D8="","",'Направление 1'!D8) | J68: =IF('Направление 1'!E8=0,"",'Направление 1'!E8)
A69: 6 | B69: =IF('Направление 1'!B9="","",'Направление 1'!B9) | E69: =IF('Направление 1'!C9="","",'Направление 1'!C9) | H69: =IF('Направление 1'!D9="","",'Направление 1'!D9) | J69: =IF('Направление 1'!E9=0,"",'Направление 1'!E9)
A70: 7 | B70: =IF('Направление 1'!B10="","",'Направление 1'!B10) | E70: =IF('Направление 1'!C10="","",'Направление 1'!C10) | H70: =IF('Направление 1'!D10="","",'Направление 1'!D10) | J70: =IF('Направление 1'!E10=0,"",'Направление 1'!E10)
A71: 8 | B71: =IF('Направление 1'!B11="","",'Направление 1'!B11) | E71: =IF('Направление 1'!C11="","",'Направление 1'!C11) | H71: =IF('Направление 1'!D11="","",'Направление 1'!D11) | J71: =IF('Направление 1'!E11=0,"",'Направление 1'!E11)
A72: 9 | B72: =IF('Направление 1'!B12="","",'Направление 1'!B12) | E72: =IF('Направление 1'!C12="","",'Направление 1'!C12) | H72: =IF('Направление 1'!D12="","",'Направление 1'!D12) | J72: =IF('Направление 1'!E12=0,"",'Направление 1'!E12)
A73: 10 | B73: =IF('Направление 1'!B13="","",'Направление 1'!B13) | E73: =IF('Направление 1'!C13="","",'Направление 1'!C13) | H73: =IF('Направление 1'!D13="","",'Направление 1'!D13) | J73: =IF('Направление 1'!E13=0,"",'Направление 1'!E13)
A74: 11 | B74: =IF('Направление 1'!B14="","",'Направление 1'!B14) | E74: =IF('Направление 1'!C14="","",'Направление 1'!C14) | H74: =IF('Направление 1'!D14="","",'Направление 1'!D14) | J74: =IF('Направление 1'!E14=0,"",'Направление 1'!E14)
A75: 12 | B75: =IF('Направление 1'!B15="","",'Направление 1'!B15) | E75: =IF('Направление 1'!C15="","",'Направление 1'!C15) | H75: =IF('Направление 1'!D15="","",'Направление 1'!D15) | J75: =IF('Направление 1'!E15=0,"",'Направление 1'!E15)
... A143: 80 | B143: =IF('Направление 1'!B83="","",'Направление 1'!B83) | E143: =IF('Направление 1'!C83="","",'Направление 1'!C83) | H143: =IF('Направление 1'!D83="","",'Направление 1'!D83) | J143: =IF('Направление 1'!E83=0,"",'Направление 1'!E83)
B144: Планиран за закупуване софтуер
B145: Наименование на софтуер | E145: Технически спецификации/характеристики | J145: Количество
A146: 1 | B146: =IF('Направление 1'!B86="","",'Направление 1'!B86) | E146: =IF('Направление 1'!C86="","",'Направление 1'!C86) | H146: =IF('Направление 1'!D86="","",'Направление 1'!D86) -> х | J146: =IF('Направление 1'!E86=0,"",'Направление 1'!E86)
A147: 2 | B147: =IF('Направление 1'!B87="","",'Направление 1'!B87) | E147: =IF('Направление 1'!C87="","",'Направление 1'!C87) | H147: =IF('Направление 1'!D87="","",'Направление 1'!D87) -> х | J147: =IF('Направление 1'!E87=0,"",'Направление 1'!E87)
A148: 3 | B148: =IF('Направление 1'!B88="","",'Направление 1'!B88) | E148: =IF('Направление 1'!C88="","",'Направление 1'!C88) | H148: =IF('Направление 1'!D88="","",'Направление 1'!D88) -> х | J148: =IF('Направление 1'!E88=0,"",'Направление 1'!E88)
A149: 4 | B149: =IF('Направление 1'!B89="","",'Направление 1'!B89) | E149: =IF('Направление 1'!C89="","",'Направление 1'!C89) | H149: =IF('Направление 1'!D89="","",'Направление 1'!D89) -> х | J149: =IF('Направление 1'!E89=0,"",'Направление 1'!E89)
A150: 5 | B150: =IF('Направление 1'!B90="","",'Направление 1'!B90) | E150: =IF('Направление 1'!C90="","",'Направление 1'!C90) | H150: =IF('Направление 1'!D90="","",'Направление 1'!D90) -> х | J150: =IF('Направление 1'!E90=0,"",'Направление 1'!E90)
A151: 6 | B151: =IF('Направление 1'!B91="","",'Направление 1'!B91) | E151: =IF('Направление 1'!C91="","",'Направление 1'!C91) | H151: =IF('Направление 1'!D91="","",'Направление 1'!D91) -> х | J151: =IF('Направление 1'!E91=0,"",'Направление 1'!E91)
A152: 7 | B152: =IF('Направление 1'!B92="","",'Направление 1'!B92) | E152: =IF('Направление 1'!C92="","",'Направление 1'!C92) | H152: =IF('Направление 1'!D92="","",'Направление 1'!D92) -> х | J152: =IF('Направление 1'!E92=0,"",'Направление 1'!E92)
A153: 8 | B153: =IF('Направление 1'!B93="","",'Направление 1'!B93) | E153: =IF('Направление 1'!C93="","",'Направление 1'!C93) | H153: =IF('Направление 1'!D93="","",'Направление 1'!D93) -> х | J153: =IF('Направление 1'!E93=0,"",'Направление 1'!E93)
A154: 9 | B154: =IF('Направление 1'!B94="","",'Направление 1'!B94) | E154: =IF('Направление 1'!C94="","",'Направление 1'!C94) | H154: =IF('Направление 1'!D94="","",'Направление 1'!D94) -> х | J154: =IF('Направление 1'!E94=0,"",'Направление 1'!E94)
A155: 10 | B155: =IF('Направление 1'!B95="","",'Направление 1'!B95) | E155: =IF('Направление 1'!C95="","",'Направление 1'!C95) | H155: =IF('Направление 1'!D95="","",'Направление 1'!D95) -> х | J155: =IF('Направление 1'!E95=0,"",'Направление 1'!E95)
A156: 11 | B156: =IF('Направление 1'!B96="","",'Направление 1'!B96) | E156: =IF('Направление 1'!C96="","",'Направление 1'!C96) | H156: =IF('Направление 1'!D96="","",'Направление 1'!D96) -> х | J156: =IF('Направление 1'!E96=0,"",'Направление 1'!E96)
A157: 12 | B157: =IF('Направление 1'!B97="","",'Направление 1'!B97) | E157: =IF('Направление 1'!C97="","",'Направление 1'!C97) | H157: =IF('Направление 1'!D97="","",'Направление 1'!D97) -> х | J157: =IF('Направление 1'!E97=0,"",'Направление 1'!E97)
... A185: 40 | B185: =IF('Направление 1'!B125="","",'Направление 1'!B125) | E185: =IF('Направление 1'!C125="","",'Направление 1'!C125) | H185: =IF('Направление 1'!D125="","",'Направление 1'!D125) -> х | J185: =IF('Направление 1'!E125=0,"",'Направление 1'!E125)
B186: Планирано за закупуване обзавеждане
B187: Наименование на обзавеждане | E187: Описание/характеристики | J187: Количество
A188: 1 | B188: =IF('Направление 1'!B128="","",'Направление 1'!B128) | E188: =IF('Направление 1'!C128="","",'Направление 1'!C128) | H188: =IF('Направление 1'!D128="","",'Направление 1'!D128) -> х | J188: =IF('Направление 1'!E128=0,"",'Направление 1'!E128)
A189: 2 | B189: =IF('Направление 1'!B129="","",'Направление 1'!B129) | E189: =IF('Направление 1'!C129="","",'Направление 1'!C129) | H189: =IF('Направление 1'!D129="","",'Направление 1'!D129) -> х | J189: =IF('Направление 1'!E129=0,"",'Направление 1'!E129)
A190: 3 | B190: =IF('Направление 1'!B130="","",'Направление 1'!B130) | E190: =IF('Направление 1'!C130="","",'Направление 1'!C130) | H190: =IF('Направление 1'!D130="","",'Направление 1'!D130) -> х | J190: =IF('Направление 1'!E130=0,"",'Направление 1'!E130)
A191: 4 | B191: =IF('Направление 1'!B131="","",'Направление 1'!B131) | E191: =IF('Направление 1'!C131="","",'Направление 1'!C131) | H191: =IF('Направление 1'!D131="","",'Направление 1'!D131) -> х | J191: =IF('Направление 1'!E131=0,"",'Направление 1'!E131)
A192: 5 | B192: =IF('Направление 1'!B132="","",'Направление 1'!B132) | E192: =IF('Направление 1'!C132="","",'Направление 1'!C132) | H192: =IF('Направление 1'!D132="","",'Направление 1'!D132) -> х | J192: =IF('Направление 1'!E132=0,"",'Направление 1'!E132)
A193: 6 | B193: =IF('Направление 1'!B133="","",'Направление 1'!B133) | E193: =IF('Направление 1'!C133="","",'Направление 1'!C133) | H193: =IF('Направление 1'!D133="","",'Направление 1'!D133) -> х | J193: =IF('Направление 1'!E133=0,"",'Направление 1'!E133)
A194: 7 | B194: =IF('Направление 1'!B134="","",'Направление 1'!B134) | E194: =IF('Направление 1'!C134="","",'Направление 1'!C134) | H194: =IF('Направление 1'!D134="","",'Направление 1'!D134) -> х | J194: =IF('Направление 1'!E134=0,"",'Направление 1'!E134)
A195: 8 | B195: =IF('Направление 1'!B135="","",'Направление 1'!B135) | E195: =IF('Направление 1'!C135="","",'Направление 1'!C135) | H195: =IF('Направление 1'!D135="","",'Направление 1'!D135) -> х | J195: =IF('Направление 1'!E135=0,"",'Направление 1'!E135)
A196: 9 | B196: =IF('Направление 1'!B136="","",'Направление 1'!B136) | E196: =IF('Направление 1'!C136="","",'Направление 1'!C136) | H196: =IF('Направление 1'!D136="","",'Направление 1'!D136) -> х | J196: =IF('Направление 1'!E136=0,"",'Направление 1'!E136)
A197: 10 | B197: =IF('Направление 1'!B137="","",'Направление 1'!B137) | E197: =IF('Направление 1'!C137="","",'Направление 1'!C137) | H197: =IF('Направление 1'!D137="","",'Направление 1'!D137) -> х | J197: =IF('Направление 1'!E137=0,"",'Направление 1'!E137)
A198: 11 | B198: =IF('Направление 1'!B138="","",'Направление 1'!B138) | E198: =IF('Направление 1'!C138="","",'Направление 1'!C138) | H198: =IF('Направление 1'!D138="","",'Направление 1'!D138) -> х | J198: =IF('Направление 1'!E138=0,"",'Направление 1'!E138)
A199: 12 | B199: =IF('Направление 1'!B139="","",'Направление 1'!B139) | E199: =IF('Направление 1'!C139="","",'Направление 1'!C139) | H199: =IF('Направление 1'!D139="","",'Направление 1'!D139) -> х | J199: =IF('Направление 1'!E139=0,"",'Направление 1'!E139)
... A267: 80 | B267: =IF('Направление 1'!B207="","",'Направление 1'!B207) | E267: =IF('Направление 1'!C207="","",'Направление 1'!C207) | H267: =IF('Направление 1'!D207="","",'Направление 1'!D207) -> х | J267: =IF('Направление 1'!E207=0,"",'Направление 1'!E207)
A268: 7.2 | B268: Направление 2 „Дизайн и 3D Прототипиране"
...

Sheet Направление 1
A1: Остойностен списък с оборудване/обзавеждане/софтуер и СМР за направление „Роботика и кибер-физични системи“
A2: № по ред | B2: Наименование на оборудване/софтуер/обзавеждане/СМР | C2: Описание/Технически спецификации/характеристики | D2: Минимално ниво на оборудването по Направлението | E2: Количество | F2: Единична цена без ДДС (лева) | G2: Общо без ДДС (лева) | H2: Общо с ДДС (лева) | I2: Източник за формиране на единична цена на вид оборудване/софтуер/обзавеждане**
A3: Част I: Планирано за закупуване оборудване
A4: 1 | E4: 0 | F4: 0 | G4: =E4*F4 -> 0 | H4: =G4*1.2 -> 0
A5: 2 | E5: 0 | F5: 0 | G5: =E5*F5 -> 0 | H5: =G5*1.2 -> 0
A6: 3 | E6: 0 | F6: 0 | G6: =E6*F6 -> 0 | H6: =G6*1.2 -> 0
A7: 4 | E7: 0 | F7: 0 | G7: =E7*F7 -> 0 | H7: =G7*1.2 -> 0
A8: 5 | E8: 0 | F8: 0 | G8: =E8*F8 -> 0 | H8: =G8*1.2 -> 0
A9: 6 | E9: 0 | F9: 0 | G9: =E9*F9 -> 0 | H9: =G9*1.2 -> 0
A10: 7 | E10: 0 | F10: 0 | G10: =E10*F10 -> 0 | H10: =G10*1.2 -> 0
A11: 8 | E11: 0 | F11: 0 | G11: =E11*F11 -> 0 | H11: =G11*1.2 -> 0
A12: 9 | E12: 0 | F12: 0 | G12: =E12*F12 -> 0 | H12: =G12*1.2 -> 0
A13: 10 | E13: 0 | F13: 0 | G13: =E13*F13 -> 0 | H13: =G13*1.2 -> 0
A14: 11 | E14: 0 | F14: 0 | G14: =E14*F14 -> 0 | H14: =G14*1.2 -> 0
A15: 12 | E15: 0 | F15: 0 | G15: =E15*F15 -> 0 | H15: =G15*1.2 -> 0
... A83: 80 | E83: 0 | F83: 0 | G83: =E83*F83 -> 0 | H83: =G83*1.2 -> 0
A84: Общо разходи за оборудване | G84: =SUM(G4:G83) -> 0 | H84: =SUM(H4:H83) -> 0
B85: Част II: Планиран за закупуване софтуер
A86: 1 | D86: х | E86: 0 | F86: 0 | G86: =E86*F86 -> 0 | H86: =G86*1.2 -> 0
A87: 2 | D87: х | E87: 0 | F87: 0 | G87: =E87*F87 -> 0 | H87: =G87*1.2 -> 0
A88: 3 | D88: х | E88: 0 | F88: 0 | G88: =E88*F88 -> 0 | H88: =G88*1.2 -> 0
A89: 4 | D89: х | E89: 0 | F89: 0 | G89: =E89*F89 -> 0 | H89: =G89*1.2 -> 0
A90: 5 | D90: х | E90: 0 | F90: 0 | G90: =E90*F90 -> 0 | H90: =G90*1.2 -> 0
A91: 6 | D91: х | E91: 0 | F91: 0 | G91: =E91*F91 -> 0 | H91: =G91*1.2 -> 0
A92: 7 | D92: х | E92: 0 | F92: 0 | G92: =E92*F92 -> 0 | H92: =G92*1.2 -> 0
A93: 8 | D93: х | E93: 0 | F93: 0 | G93: =E93*F93 -> 0 | H93: =G93*1.2 -> 0
A94: 9 | D94: х | E94: 0 | F94: 0 | G94: =E94*F94 -> 0 | H94: =G94*1.2 -> 0
A95: 10 | D95: х | E95: 0 | F95: 0 | G95: =E95*F95 -> 0 | H95: =G95*1.2 -> 0
A96: 11 | D96: х | E96: 0 | F96: 0 | G96: =E96*F96 -> 0 | H96: =G96*1.2 -> 0
A97: 12 | D97: х | E97: 0 | F97: 0 | G97: =E97*F97 -> 0 | H97: =G97*1.2 -> 0
... A125: 40 | D125: х | E125: 0 | F125: 0 | G125: =E125*F125 -> 0 | H125: =G125*1.2 -> 0
A126: Общо разходи за софтуер | G126: =SUM(G86:G125) -> 0 | H126: =SUM(H86:H125) -> 0
B127: Част III: Планирано за закупуване обзавеждане
A128: 1 | D128: х | E128: 0 | F128: 0 | G128: =E128*F128 -> 0 | H128: =G128*1.2 -> 0
A129: 2 | D129: х | E129: 0 | F129: 0 | G129: =E129*F129 -> 0 | H129: =G129*1.2 -> 0
A130: 3 | D130: х | E130: 0 | F130: 0 | G130: =E130*F130 -> 0 | H130: =G130*1.2 -> 0
A131: 4 | D131: х | E131: 0 | F131: 0 | G131: =E131*F131 -> 0 | H131: =G131*1.2 -> 0
A132: 5 | D132: х | E132: 0 | F132: 0 | G132: =E132*F132 -> 0 | H132: =G132*1.2 -> 0
A133: 6 | D133: х | E133: 0 | F133: 0 | G133: =E133*F133 -> 0 | H133: =G133*1.2 -> 0
A134: 7 | D134: х | E134: 0 | F134: 0 | G134: =E134*F134 -> 0 | H134: =G134*1.2 -> 0
A135: 8 | D135: х | E135: 0 | F135: 0 | G135: =E135*F135 -> 0 | H135: =G135*1.2 -> 0
A136: 9 | D136: х | E136: 0 | F136: 0 | G136: =E136*F136 -> 0 | H136: =G136*1.2 -> 0
A137: 10 | D137: х | E137: 0 | F137: 0 | G137: =E137*F137 -> 0 | H137: =G137*1.2 -> 0
A138: 11 | D138: х | E138: 0 | F138: 0 | G138: =E138*F138 -> 0 | H138: =G138*1.2 -> 0
A139: 12 | D139: х | E139: 0 | F139: 0 | G139: =E139*F139 -> 0 | H139: =G139*1.2 -> 0
... A207: 80 | D207: х | E207: 0 | F207: 0 | G207: =E207*F207 -> 0 | H207: =G207*1.2 -> 0
A208: Общо разходи за обзавеждане | G208: =SUM(G128:G207) -> 0 | H208: =SUM(H128:H207) -> 0
A209: Част IV: Разходи за СМР
A210: 1 | D210: х | E210: 1 | F210: 0 | G210: =E210*F210 -> 0 | H210: =G210*1.2 -> 0 | I210: -
A211: Общо разходи за СМР | G211: =SUM(G210:G210) -> 0 | H211: =SUM(H210:H210) -> 0
A212: Общо разходи за оборудване/обзавеждане/софтуер/СМР | G212: =G84+G126+G208+G211 -> 0 | H212: =H84+H126+H208+H211 -> 0
A213: ** В колона "Източник за формиране на единична цена на вид оборудване/софтуер/обзавеждане" се посочват подходящи източници на информация, въз основа на които са определени планираните стойности на разходите - проучвания в интернет (хиперлинкове към съответните интернет базирани източници) и/или номер и дата на оферта/и . ***С оглед коректното изчисляване на размера на исканото финансиране за изграждане на училищна STEM среда в част IV. Разходи за СМР, те се посочват общо, без да е необходимо тяхното описание, и за тях не се посочва източник за формиране на единична цена.

Sheet Направление 2
A1: Остойностен списък с оборудване/обзавеждане/софтуер и СМР за направление „Дизайн и 3D Прототипиране“
A2: № по ред | B2: Наименование на оборудване/софтуер/обзавеждане/СМР | C2: Описание/Технически спецификации/характеристики | D2: Минимално ниво на оборудването по Направлението | E2: Количество | F2: Единична цена без ДДС (лева) | G2: Общо без ДДС (лева) | H2: Общо с ДДС (лева) | I2: Източник за формиране на единична цена на вид оборудване/софтуер/обзавеждане**
A3: Част I: Планирано за закупуване оборудване
A4: 1 | E4: 0 | F4: 0 | G4: =E4*F4 -> 0 | H4: =G4*1.2 -> 0
A5: 2 | E5: 0 | F5: 0 | G5: =E5*F5 -> 0 | H5: =G5*1.2 -> 0
A6: 3 | E6: 0 | F6: 0 | G6: =E6*F6 -> 0 | H6: =G6*1.2 -> 0
A7: 4 | E7: 0 | F7: 0 | G7: =E7*F7 -> 0 | H7: =G7*1.2 -> 0
A8: 5 | E8: 0 | F8: 0 | G8: =E8*F8 -> 0 | H8: =G8*1.2 -> 0
A9: 6 | E9: 0 | F9: 0 | G9: =E9*F9 -> 0 | H9: =G9*1.2 -> 0
A10: 7 | E10: 0 | F10: 0 | G10: =E10*F10 -> 0 | H10: =G10*1.2 -> 0
A11: 8 | E11: 0 | F11: 0 | G11: =E11*F11 -> 0 | H11: =G11*1.2 -> 0
A12: 9 | E12: 0 | F12: 0 | G12: =E12*F12 -> 0 | H12: =G12*1.2 -> 0
A13: 10 | E13: 0 | F13: 0 | G13: =E13*F13 -> 0 | H13: =G13*1.2 -> 0
A14: 11 | E14: 0 | F14: 0 | G14: =E14*F14 -> 0 | H14: =G14*1.2 -> 0
A15: 12 | E15: 0 | F15: 0 | G15: =E15*F15 -> 0 | H15: =G15*1.2 -> 0
... A83: 80 | E83: 0 | F83: 0 | G83: =E83*F83 -> 0 | H83: =G83*1.2 -> 0
A84: Общо разходи за оборудване | G84: =SUM(G4:G83) -> 0 | H84: =SUM(H4:H83) -> 0
B85: Част II: Планиран за закупуване софтуер
A86: 1 | D86: х | E86: 0 | F86: 0 | G86: =E86*F86 -> 0 | H86: =G86*1.2 -> 0
A87: 2 | D87: х | E87: 0 | F87: 0 | G87: =E87*F87 -> 0 | H87: =G87*1.2 -> 0
A88: 3 | D88: х | E88: 0 | F88: 0 | G88: =E88*F88 -> 0 | H88: =G88*1.2 -> 0
A89: 4 | D89: х | E89: 0 | F89: 0 | G89: =E89*F89 -> 0 | H89: =G89*1.2 -> 0
A90: 5 | D90: х | E90: 0 | F90: 0 | G90: =E90*F90 -> 0 | H90: =G90*1.2 -> 0
A91: 6 | D91: х | E91: 0 | F91: 0 | G91: =E91*F91 -> 0 | H91: =G91*1.2 -> 0
A92: 7 | D92: х | E92: 0 | F92: 0 | G92: =E92*F92 -> 0 | H92: =G92*1.2 -> 0
A93: 8 | D93: х | E93: 0 | F93: 0 | G93: =E93*F93 -> 0 | H93: =G93*1.2 -> 0
A94: 9 | D94: х | E94: 0 | F94: 0 | G94: =E94*F94 -> 0 | H94: =G94*1.2 -> 0
A95: 10 | D95: х | E95: 0 | F95: 0 | G95: =E95*F95 -> 0 | H95: =G95*1.2 -> 0
A96: 11 | D96: х | E96: 0 | F96: 0 | G96: =E96*F96 -> 0 | H96: =G96*1.2 -> 0
A97: 12 | D97: х | E97: 0 | F97: 0 | G97: =E97*F97 -> 0 | H97: =G97*1.2 -> 0
... A125: 40 | D125: х | E125: 0 | F125: 0 | G125: =E125*F125 -> 0 | H125: =G125*1.2 -> 0
A126: Общо разходи за софтуер | G126: =SUM(G86:G125) -> 0 | H126: =SUM(H86:H125) -> 0
B127: Част III: Планирано за закупуване обзавеждане
A128: 1 | D128: х | E128: 0 | F128: 0 | G128: =E128*F128 -> 0 | H128: =G128*1.2 -> 0
A129: 2 | D129: х | E129: 0 | F129: 0 | G129: =E129*F129 -> 0 | H129: =G129*1.2 -> 0
A130: 3 | D130: х | E130: 0 | F130: 0 | G130: =E130*F130 -> 0 | H130: =G130*1.2 -> 0
A131: 4 | D131: х | E131: 0 | F131: 0 | G131: =E131*F131 -> 0 | H131: =G131*1.2 -> 0
A132: 5 | D132: х | E132: 0 | F132: 0 | G132: =E132*F132 -> 0 | H132: =G132*1.2 -> 0
A133: 6 | D133: х | E133: 0 | F133: 0 | G133: =E133*F133 -> 0 | H133: =G133*1.2 -> 0
A134: 7 | D134: х | E134: 0 | F134: 0 | G134: =E134*F134 -> 0 | H134: =G134*1.2 -> 0
A135: 8 | D135: х | E135: 0 | F135: 0 | G135: =E135*F135 -> 0 | H135: =G135*1.2 -> 0
A136: 9 | D136: х | E136: 0 | F136: 0 | G136: =E136*F136 -> 0 | H136: =G136*1.2 -> 0
A137: 10 | D137: х | E137: 0 | F137: 0 | G137: =E137*F137 -> 0 | H137: =G137*1.2 -> 0
A138: 11 | D138: х | E138: 0 | F138: 0 | G138: =E138*F138 -> 0 | H138: =G138*1.2 -> 0
A139: 12 | D139: х | E139: 0 | F139: 0 | G139: =E139*F139 -> 0 | H139: =G139*1.2 -> 0
... A207: 80 | D207: х | E207: 0 | F207: 0 | G207: =E207*F207 -> 0 | H207: =G207*1.2 -> 0
A208: Общо разходи за обзавеждане | G208: =SUM(G128:G207) -> 0 | H208: =SUM(H128:H207) -> 0
A209: Част IV: Разходи за СМР
A210: 1 | D210: х | E210: 1 | F210: 0 | G210: =E210*F210 -> 0 | H210: =G210*1.2 -> 0 | I210: -
A211: Общо разходи за СМР | G211: =SUM(G210:G210) -> 0 | H211: =SUM(H210:H210) -> 0
A212: Общо разходи за оборудване/обзавеждане/софтуер/СМР | G212: =G84+G126+G208+G211 -> 0 | H212: =H84+H126+H208+H211 -> 0
A213: ** В колона "Източник за формиране на единична цена на вид оборудване/софтуер/обзавеждане" се посочват подходящи източници на информация, въз основа на които са определени планираните стойности на разходите - проучвания в интернет (хиперлинкове към съответните интернет базирани източници) и/или номер и дата на оферта/и . ***С оглед коректното изчисляване на размера на исканото финансиране за изграждане на училищна STEM среда в част IV. Разходи за СМР, те се посочват общо, без да е необходимо тяхното описание, и за тях не се посочва източник за формиране на единична цена.

Sheet Направление 3
A1: Остойностен списък с оборудване/обзавеждане/софтуер и СМР за направление „Природни науки“
A2: № по ред | B2: Наименование на оборудване/софтуер/обзавеждане/СМР | C2: Описание/Технически спецификации/характеристики | D2: Минимално ниво на оборудването по Направлението | E2: Количество | F2: Единична цена без ДДС (лева) | G2: Общо без ДДС (лева) | H2: Общо с ДДС (лева) | I2: Източник за формиране на единична цена на вид оборудване/софтуер/обзавеждане**
A3: Част I: Планирано за закупуване оборудване
A4: 1 | E4: 0 | F4: 0 | G4: =E4*F4 -> 0 | H4: =G4*1.2 -> 0
A5: 2 | E5: 0 | F5: 0 | G5: =E5*F5 -> 0 | H5: =G5*1.2 -> 0
A6: 3 | E6: 0 | F6: 0 | G6: =E6*F6 -> 0 | H6: =G6*1.2 -> 0
A7: 4 | E7: 0 | F7: 0 | G7: =E7*F7 -> 0 | H7: =G7*1.2 -> 0
A8: 5 | E8: 0 | F8: 0 | G8: =E8*F8 -> 0 | H8: =G8*1.2 -> 0
A9: 6 | E9: 0 | F9: 0 | G9: =E9*F9 -> 0 | H9: =G9*1.2 -> 0
A10: 7 | E10: 0 | F10: 0 | G10: =E10*F10 -> 0 | H10: =G10*1.2 -> 0
A11: 8 | E11: 0 | F11: 0 | G11: =E11*F11 -> 0 | H11: =G11*1.2 -> 0
A12: 9 | E12: 0 | F12: 0 | G12: =E12*F12 -> 0 | H12: =G12*1.2 -> 0
A13: 10 | E13: 0 | F13: 0 | G13: =E13*F13 -> 0 | H13: =G13*1.2 -> 0
A14: 11 | E14: 0 | F14: 0 | G14: =E14*F14 -> 0 | H14: =G14*1.2 -> 0
A15: 12 | E15: 0 | F15: 0 | G15: =E15*F15 -> 0 | H15: =G15*1.2 -> 0
... A83: 80 | E83: 0 | F83: 0 | G83: =E83*F83 -> 0 | H83: =G83*1.2 -> 0
A84: Общо разходи за оборудване | G84: =SUM(G4:G83) -> 0 | H84: =SUM(H4:H83) -> 0
B85: Част II: Планиран за закупуване софтуер
A86: 1 | D86: х | E86: 0 | F86: 0 | G86: =E86*F86 -> 0 | H86: =G86*1.2 -> 0
A87: 2 | D87: х | E87: 0 | F87: 0 | G87: =E87*F87 -> 0 | H87: =G87*1.2 -> 0
A88: 3 | D88: х | E88: 0 | F88: 0 | G88: =E88*F88 -> 0 | H88: =G88*1.2 -> 0
A89: 4 | D89: х | E89: 0 | F89: 0 | G89: =E89*F89 -> 0 | H89: =G89*1.2 -> 0
A90: 5 | D90: х | E90: 0 | F90: 0 | G90: =E90*F90 -> 0 | H90: =G90*1.2 -> 0
A91: 6 | D91: х | E91: 0 | F91: 0 | G91: =E91*F91 -> 0 | H91: =G91*1.2 -> 0
A92: 7 | D92: х | E92: 0 | F92: 0 | G92: =E92*F92 -> 0 | H92: =G92*1.2 -> 0
A93: 8 | D93: х | E93: 0 | F93: 0 | G93: =E93*F93 -> 0 | H93: =G93*1.2 -> 0
A94: 9 | D94: х | E94: 0 | F94: 0 | G94: =E94*F94 -> 0 | H94: =G94*1.2 -> 0
A95: 10 | D95: х | E95: 0 | F95: 0 | G95: =E95*F95 -> 0 | H95: =G95*1.2 -> 0
A96: 11 | D96: х | E96: 0 | F96: 0 | G96: =E96*F96 -> 0 | H96: =G96*1.2 -> 0
A97: 12 | D97: х | E97: 0 | F97: 0 | G97: =E97*F97 -> 0 | H97: =G97*1.2 -> 0
... A125: 40 | D125: х | E125: 0 | F125: 0 | G125: =E125*F125 -> 0 | H125: =G125*1.2 -> 0
A126: Общо разходи за софтуер | G126: =SUM(G86:G125) -> 0 | H126: =SUM(H86:H125) -> 0
B127: Част III: Планирано за закупуване обзавеждане
A128: 1 | D128: х | E128: 0 | F128: 0 | G128: =E128*F128 -> 0 | H128: =G128*1.2 -> 0
A129: 2 | D129: х | E129: 0 | F129: 0 | G129: =E129*F129 -> 0 | H129: =G129*1.2 -> 0
A130: 3 | D130: х | E130: 0 | F130: 0 | G130: =E130*F130 -> 0 | H130: =G130*1.2 -> 0
A131: 4 | D131: х | E131: 0 | F131: 0 | G131: =E131*F131 -> 0 | H131: =G131*1.2 -> 0
A132: 5 | D132: х | E132: 0 | F132: 0 | G132: =E132*F132 -> 0 | H132: =G132*1.2 -> 0
A133: 6 | D133: х | E133: 0 | F133: 0 | G133: =E133*F133 -> 0 | H133: =G133*1.2 -> 0
A134: 7 | D134: х | E134: 0 | F134: 0 | G134: =E134*F134 -> 0 | H134: =G134*1.2 -> 0
A135: 8 | D135: х | E135: 0 | F135: 0 | G135: =E135*F135 -> 0 | H135: =G135*1.2 -> 0
A136: 9 | D136: х | E136: 0 | F136: 0 | G136: =E136*F136 -> 0 | H136: =G136*1.2 -> 0
A137: 10 | D137: х | E137: 0 | F137: 0 | G137: =E137*F137 -> 0 | H137: =G137*1.2 -> 0
A138: 11 | D138: х | E138: 0 | F138: 0 | G138: =E138*F138 -> 0 | H138: =G138*1.2 -> 0
A139: 12 | D139: х | E139: 0 | F139: 0 | G139: =E139*F139 -> 0 | H139: =G139*1.2 -> 0
... A207: 80 | D207: х | E207: 0 | F207: 0 | G207: =E207*F207 -> 0 | H207: =G207*1.2 -> 0
A208: Общо разходи за обзавеждане | G208: =SUM(G128:G207) -> 0 | H208: =SUM(H128:H207) -> 0
A209: Част IV: Разходи за СМР
A210: 1 | D210: х | E210: 1 | F210: 0 | G210: =E210*F210 -> 0 | H210: =G210*1.2 -> 0 | I210: -
A211: Общо разходи за СМР | G211: =SUM(G210:G210) -> 0 | H211: =SUM(H210:H210) -> 0
A212: Общо разходи за оборудване/обзавеждане/софтуер/СМР | G212: =G84+G126+G208+G211 -> 0 | H212: =H84+H126+H208+H211 -> 0
A213: ** В колона "Източник за формиране на единична цена на вид оборудване/софтуер/обзавеждане" се посочват подходящи източници на информация, въз основа на които са определени планираните стойности на разходите - проучвания в интернет (хиперлинкове към съответните интернет базирани източници) и/или номер и дата на оферта/и . ***С оглед коректното изчисляване на размера на исканото финансиране за изграждане на училищна STEM среда в част IV. Разходи за СМР, те се посочват общо, без да е необходимо тяхното описание, и за тях не се посочва източник за формиране на единична цена.

Sheet Направление 4
A1: Остойностен списък с оборудване/обзавеждане/софтуер и СМР за направление „Зелени технологии и устойчиво развитие“
A2: № по ред | B2: Наименование на оборудване/софтуер/обзавеждане/СМР | C2: Описание/Технически спецификации/характеристики | D2: Минимално ниво на оборудването по Направлението | E2: Количество | F2: Единична цена без ДДС (лева) | G2: Общо без ДДС (лева) | H2: Общо с ДДС (лева) | I2: Източник за формиране на единична цена на вид оборудване/софтуер/обзавеждане**
A3: Част I: Планирано за закупуване оборудване
A4: 1 | E4: 0 | F4: 0 | G4: =E4*F4 -> 0 | H4: =G4*1.2 -> 0
A5: 2 | E5: 0 | F5: 0 | G5: =E5*F5 -> 0 | H5: =G5*1.2 -> 0
A6: 3 | E6: 0 | F6: 0 | G6: =E6*F6 -> 0 | H6: =G6*1.2 -> 0
A7: 4 | E7: 0 | F7: 0 | G7: =E7*F7 -> 0 | H7: =G7*1.2 -> 0
A8: 5 | E8: 0 | F8: 0 | G8: =E8*F8 -> 0 | H8: =G8*1.2 -> 0
A9: 6 | E9: 0 | F9: 0 | G9: =E9*F9 -> 0 | H9: =G9*1.2 -> 0
A10: 7 | E10: 0 | F10: 0 | G10: =E10*F10 -> 0 | H10: =G10*1.2 -> 0
A11: 8 | E11: 0 | F11: 0 | G11: =E11*F11 -> 0 | H11: =G11*1.2 -> 0
A12: 9 | E12: 0 | F12: 0 | G12: =E12*F12 -> 0 | H12: =G12*1.2 -> 0
A13: 10 | E13: 0 | F13: 0 | G13: =E13*F13 -> 0 | H13: =G13*1.2 -> 0
A14: 11 | E14: 0 | F14: 0 | G14: =E14*F14 -> 0 | H14: =G14*1.2 -> 0
A15: 12 | E15: 0 | F15: 0 | G15: =E15*F15 -> 0 | H15: =G15*1.2 -> 0
... A83: 80 | E83: 0 | F83: 0 | G83: =E83*F83 -> 0 | H83: =G83*1.2 -> 0
A84: Общо разходи за оборудване | G84: =SUM(G4:G83) -> 0 | H84: =SUM(H4:H83) -> 0
B85: Част II: Планиран за закупуване софтуер
A86: 1 | D86: х | E86: 0 | F86: 0 | G86: =E86*F86 -> 0 | H86: =G86*1.2 -> 0
A87: 2 | D87: х | E87: 0 | F87: 0 | G87: =E87*F87 -> 0 | H87: =G87*1.2 -> 0
A88: 3 | D88: х | E88: 0 | F88: 0 | G88: =E88*F88 -> 0 | H88: =G88*1.2 -> 0
A89: 4 | D89: х | E89: 0 | F89: 0 | G89: =E89*F89 -> 0 | H89: =G89*1.2 -> 0
A90: 5 | D90: х | E90: 0 | F90: 0 | G90: =E90*F90 -> 0 | H90: =G90*1.2 -> 0
A91: 6 | D91: х | E91: 0 | F91: 0 | G91: =E91*F91 -> 0 | H91: =G91*1.2 -> 0
A92: 7 | D92: х | E92: 0 | F92: 0 | G92: =E92*F92 -> 0 | H92: =G92*1.2 -> 0
A93: 8 | D93: х | E93: 0 | F93: 0 | G93: =E93*F93 -> 0 | H93: =G93*1.2 -> 0
A94: 9 | D94: х | E94: 0 | F94: 0 | G94: =E94*F94 -> 0 | H94: =G94*1.2 -> 0
A95: 10 | D95: х | E95: 0 | F95: 0 | G95: =E95*F95 -> 0 | H95: =G95*1.2 -> 0
A96: 11 | D96: х | E96: 0 | F96: 0 | G96: =E96*F96 -> 0 | H96: =G96*1.2 -> 0
A97: 12 | D97: х | E97: 0 | F97: 0 | G97: =E97*F97 -> 0 | H97: =G97*1.2 -> 0
... A125: 40 | D125: х | E125: 0 | F125: 0 | G125: =E125*F125 -> 0 | H125: =G125*1.2 -> 0
A126: Общо разходи за софтуер | G126: =SUM(G86:G125) -> 0 | H126: =SUM(H86:H125) -> 0
B127: Част III: Планирано за закупуване обзавеждане
A128: 1 | D128: х | E128: 0 | F128: 0 | G128: =E128*F128 -> 0 | H128: =G128*1.2 -> 0
A129: 2 | D129: х | E129: 0 | F129: 0 | G129: =E129*F129 -> 0 | H129: =G129*1.2 -> 0
A130: 3 | D130: х | E130: 0 | F130: 0 | G130: =E130*F130 -> 0 | H130: =G130*1.2 -> 0
A131: 4 | D131: х | E131: 0 | F131: 0 | G131: =E131*F131 -> 0 | H131: =G131*1.2 -> 0
A132: 5 | D132: х | E132: 0 | F132: 0 | G132: =E132*F132 -> 0 | H132: =G132*1.2 -> 0
A133: 6 | D133: х | E133: 0 | F133: 0 | G133: =E133*F133 -> 0 | H133: =G133*1.2 -> 0
A134: 7 | D134: х | E134: 0 | F134: 0 | G134: =E134*F134 -> 0 | H134: =G134*1.2 -> 0
A135: 8 | D135: х | E135: 0 | F135: 0 | G135: =E135*F135 -> 0 | H135: =G135*1.2 -> 0
A136: 9 | D136: х | E136: 0 | F136: 0 | G136: =E136*F136 -> 0 | H136: =G136*1.2 -> 0
A137: 10 | D137: х | E137: 0 | F137: 0 | G137: =E137*F137 -> 0 | H137: =G137*1.2 -> 0
A138: 11 | D138: х | E138: 0 | F138: 0 | G138: =E138*F138 -> 0 | H138: =G138*1.2 -> 0
A139: 12 | D139: х | E139: 0 | F139: 0 | G139: =E139*F139 -> 0 | H139: =G139*1.2 -> 0
... A207: 80 | D207: х | E207: 0 | F207: 0 | G207: =E207*F207 -> 0 | H207: =G207*1.2 -> 0
A208: Общо разходи за обзавеждане | G208: =SUM(G128:G207) -> 0 | H208: =SUM(H128:H207) -> 0
A209: Част IV: Разходи за СМР
A210: 1 | D210: х | E210: 1 | F210: 0 | G210: =E210*F210 -> 0 | H210: =G210*1.2 -> 0 | I210: -
A211: Общо разходи за СМР | G211: =SUM(G210:G210) -> 0 | H211: =SUM(H210:H210) -> 0
A212: Общо разходи за оборудване/обзавеждане/софтуер/СМР | G212: =G84+G126+G208+G211 -> 0 | H212: =H84+H126+H208+H211 -> 0
A213: ** В колона "Източник за формиране на единична цена на вид оборудване/софтуер/обзавеждане" се посочват подходящи източници на информация, въз основа на които са определени планираните стойности на разходите - проучвания в интернет (хиперлинкове към съответните интернет базирани източници) и/или номер и дата на оферта/и . ***С оглед коректното изчисляване на размера на исканото финансиране за изграждане на училищна STEM среда в част IV. Разходи за СМР, те се посочват общо, без да е необходимо тяхното описание, и за тях не се посочва източник за формиране на единична цена.

Sheet Направление 5
A1: Остойностен списък с оборудване/обзавеждане/софтуер и СМР за направление „Математика и Информатика“
A2: № по ред | B2: Наименование на оборудване/софтуер/обзавеждане/СМР | C2: Описание/Технически спецификации/характеристики | D2: Минимално ниво на оборудването по Направлението | E2: Количество | F2: Единична цена без ДДС (лева) | G2: Общо без ДДС (лева) | H2: Общо с ДДС (лева) | I2: Източник за формиране на единична цена на вид оборудване/софтуер/обзавеждане**
A3: Част I: Планирано за закупуване оборудване
A4: 1 | B4: преносим компютър | C4: Процесор: 3.30 GHz, 10 MB cache Памет: 8GB 3200GHz DDR4 Диск: SSD 512GB Дисплей: 15.6'' , 1920x1080 dpi Мрежа: 10/100/1000 Mbps Безжична мрежа: 802.11ac 1x1 WiFi, Bluetooth Портове, 1 х USB 3.2 Gen 1, 1 х USB 2.0, 1 х HDMI Web камера: HD cam Кирилизация БДС кирилизация на клавиатурата Инсталирана операционна система | D4: преносим компютър | E4: 45 | F4: 1232.5 | G4: =E4*F4 -> 55462.5 | H4: =G4*1.2 -> 66555 | I4: https://www.ozone.bg/product/laptop-dell-vostro-3530-intel-core-5-1335u-12-mb-cache-up-to-4-60-ghz-15-6-fhd-1920x1080-ag-120hz-wva-250nits-8gb-1x8gb-ddr4-512gb-pcie-m-2-uhd-graphics-hd-cam-and-mic-802-11ac-bg-kb-win-11-pro-3y-bos/ - 1699 лв с ДДС https://ardes.bg/product/dell-vostro-3520-n1614pvnb3520emea01-ubu-16gb-w11h-317367 - 1178 лв с ддс
A5: 2 | B5: Интерактивен дисплей с широкоъгълна камера и микрофон | C5: 65-инчов 4K интерактивен плосък панел с камера и микрофон, с OPS/OPS-C устройства, реализирайки плавно превключване между вградените системи. | D5: интерактивен дисплей | E5: 3 | F5: 6185 | G5: =E5*F5 -> 18555 | H5: =G5*1.2 -> 22266 | I5: https://ont.bg/bg-product-details-158.html - 6048 лв с ддс https://www.jmt.bg/newline-tt-6522z-pid78504 - 8897 лв с ддс
A6: 3 | B6: Рутер, 5.4Gbps, черен | C6: Брой антени 6 Тип охлаждане Пасивно Wi-Fi скорост (Mbps) до 5400 Сигурност WPA/WPA2-Enterprise, WPA2, WPA3 Портове USB 3, RJ45 Цвят Черен Тегло 1.554 kg Подходящ за За дома, Офиса, Работа Интерес Технологии Размер на опаковката 33 x 12.3 x 26.7 cm Гаранция 36 месеца | D6: мрежово оборудване | E6: 3 | F6: 358.89 | G6: =E6*F6 -> 1076.67 | H6: =G6*1.2 -> 1292.004 | I6: https://www.ozone.bg/product/ruter-ubiquiti-edgerouter-4-er-4/ - 424.15 лв с ддс https://www.senetic.bg/product/Archer_AXE75?gclid=CjwKCAjwhJukBhBPEiwAniIcNbRIJRtkjYYCUmD0ZTKvhfRwv3d1ujC9Ky3D1i7maGRIk-r1MpMNKxoC7zwQAvD_BwE - 424.52 лв с ддс
A7: 4 | B7: Очила за виртуална реалност | C7: Дисплей: LCD (1832x1920) двоен дисплей Вградена памет: 128 GB Интерфейс: USB Type C Аудио: Вградени говорители Сензори: Акселерометър Жироскоп Сензор за близост Лазерни сензори за позициониране Размер: 260 x 180.7 x 126 мм Тегло: 830 г Съвместимост: със смартфони с инсталирано приложение Аксесоари: контролери за допир в комплекта Гаранционен срок: 24 месеца гаранция | D7: 3D очила | E7: 28 | F7: 857.5 | G7: =E7*F7 -> 24010 | H7: =G7*1.2 -> 28812 | I7: https://ardes.bg/product/oculus-quest-2-128gb-all-in-one-byal-301-00355-01-276169?utm_source=pazaruvaj.com&utm_medium=VR+%D0%BE%D1%87%D0%B8%D0%BB%D0%B0 949 лв с ддс https://bestpc.bg/bg/aksesoari-drugi/facebook/komplekt-za-virtualna-realnost-oculus-quest-2-256gb-295270 1109 лв с ддс
A8: 5 | B8: Платки | C8: Комплект за програмиране с многобройни компоненти | D8: контролерни платки с микроконтролери или микропроцесори | E8: 3 | F8: 56.3 | G8: =E8*F8 -> 168.9 | H8: =G8*1.2 -> 202.68 | I8: https://vikiwat.com/prototipna-platka-razvoen-komplekt-arduino-uno-rev3-bg.html 75.11лв с ддс https://erelement.com/arduino-ethernet-shield-2 60лв с ддс
A9: 6 | B9: Режещ плотер | C9: Максимална ширина на медията 719 мм Максимална ширина на рязане 600 мм Тип на моторите Стъпков Максимална скорост на рязане 705 мм/сек Максимална дебелина на медията 0.8 мм Натиск на ножа до 350 гр Система за засичане на пасери и рязане на отпечатани изображения по контур не Механична резолюция 0.006 мм Софтуерна резолюция 0.025 мм Повторяемост ± 0.1 мм Начална точка на рязане Да Перфорация Да Размножаване Да Повторение Да Памет/буфер 512 КB Софтуер Дисплей за управление 6 LED, 10 бутона Диаметър на ножчетата 2.5 мм Размери 233 х 255 х 880 мм. Захранване 100 to 240 V AC, 50/60 Hz Работна среда 15'C to 30'C, 25% to 75% RH | D9: плотер | E9: 2 | F9: 1007.9 | G9: =E9*F9 -> 2015.8 | H9: =G9*1.2 -> 2418.96 | I9: https://www.adcom.bg/produkti/rejeshti-ploteri/rolni/expert-ii-24-detail 1432.8 с ддс https://hansbg.com/product/7781/rezhesht-ploter-expert-ii-24-lx.html 986.15лв
A10: 7 | B10: 3D Принтер | C10: Технология на 3D печат: FDM или еквивалент; Тип на използваните материали: минимум PLA или еквивалент; Размери на работната област за изграждане на модели минимум: 280х190х160mm; Скорост на изграждане: до 100 mm/s; Точност на изграждане: 0.2 mm; Височина на слоя при изграждане: 0.1 до 0.3 mm; Диаметър на филамент: минимум 1.75mm. Дюза: минимум 1 брой, диаметър: 0.4 mm, температура на нагряване на дюзата: минимум до 190° C; Температура на работна област за изграждане: минимум до 60° C; Екран; Софтуер за управление и подготовка на детайли за печат. | D10: 3D Принтер | E10: 2 | F10: 990.89 | G10: =E10*F10 -> 1981.78 | H10: =G10*1.2 -> 2378.136 | I10: https://www.emag.bg/3d-printer-wanhao-duplicator-7-plus-dlp-12x6-8x18-cm-cveten-tychskrijn-d7plus/pd/DXRWR5BBM/?_gl=1*6kclas*_up*MQ..&gclid=CjwKCAjwyqWkBhBMEiwAp2yUFkYUEmmdIPZQRpb7r8RhSc5fuPE-usVOuKwoUd5gWSWfMMAcqEOQlxoC5hwQAvD_BwE - 1213,20 лв с ддс https://3dprintx.bg/magazin/k1c-creality/ - 1228 лв.с ддс
A11: 8 | B11: HDMI кабел | C11: HDMI кабел 15м | D11: мрежово оборудване | E11: 10 | F11: 82.5 | G11: =E11*F11 -> 825 | H11: =G11*1.2 -> 990 | I11: https://dice.bg/belkin-8k-ultra-high-speed-hdmi-cable-with-dolby-vision-hdmi-kabel-s-poddrazhka-na-dolby-vision-200-sm-cheren-item36117/ - 99 лв с ддс https://www.jarcomputers.com/belkin-8k-ultra-high-speed-hdmi-cable-with-dolby-vision-hdmi-kabel-s-poddryjka-na-dolby-vi_sprod_413629.html - 99 лв с ддс
A12: 9 | B12: суич-комутатор | C12: Вид продукт Суич Напрежение 100 - 240 V Честота 50/60 Hz Температура -5°C - 40°C Портове LAN 10/100 Mbps, 16 x 10/100/1000Mbps Wifi Стандарт IEEE 802.3 at, IEEE 802.3ad, IEEE 802.3af Ethernet скорост 10/100/1000 Mbps Тип охлаждане Активно Сигурност ESD/EMP Портове 2x SFP Цвят Бял Подходящ за Бизнес, За дома, Офиса, Работа Размер на продукта 44.3 x 4.37 x 20 cm Гаранция 24 месеца Тегло на продукта 2.8 kg | D12: мрежово оборудване | E12: 2 | F12: 662.68 | G12: =E12*F12 -> 1325.36 | H12: =G12*1.2 -> 1590.432 | I12: https://www.ozone.bg/product/16-portov-gigabiten-komutator-ubiquiti-usw-16-poe-gen2/ 999 лв с ддс https://www.senetic.bg/product/USW-16-POE?gclid=CjwKCAjwhJukBhBPEiwAniIcNfnBbHTFT4xonsu4nT9CzpPaEG_NgTyeqUMPj0BDPhBoANkb_5y2ahoC0RwQAvD_BwE 591,43 лв с ДДС
A13: 10 | B13: видеорегистратор | C13: Видео компресия H.265/H.264 Резолюция на кодиране Поток с висока разделителна способност: 1080p/720p/WD1/4CIF/VGA/CIF Поток със стандартна разделителна способност: WD1/4CIF/CIF Плавен поток: CIF/QVGA Честота на кадрите 1 до 25 fps (P)/30 fps (N) Видео битрейт 32 Kbps до 16 Mbps Тип поток Видео и аудио, видео Аудио компресия AAC Аудио битрейт 128 Kbps Видео и аудио IP видео вход 5-канал; До 2 MP резолюция; Поддържа H.265/H.264 IP камери Аналогов видео вход 8-кан; наличие на интерфейс ; 1080p/25 fps, 1080p/30 fps, 720p/25 fps, 720p/30 fps, 720p/50 fps, 720p/60 fps; Възможност за свързване към CVBS сигнал HDMI изход 1-канал; 1024 × 768/60 Hz, 1280 × 720/60 Hz, 1280 × 1024/60 Hz, 1920 × 1080/60 Hz VGA изход 1-канал; 1024 × 768/60 Hz, 1280 × 720/60 Hz, 1280 × 1024/60 Hz, 1920 × 1080/60 Hz HDMI вход 2-канал; 1024 × 768, 1280 × 720, 1366 × 768, 1680 × 1050, 1920 × 1080; HDMI и VGA не могат да бъдат разпознати синхронно в една и съща група VGA вход 2 канала; 1024 × 768, 1280 × 720, 1366 × 768, 1680 × 1050, 1920 × 1080; HDMI и VGA не могат да бъдат разпознати синхронно в една и съща група HDMI Loopback 1 канал (съвпадение на HDMI видео в 1) VGA Loopback 1 канал (съвпадение на VGA видео в 1) Аудио изход 1-канален двоен канал на 3,5 мм конектор 1-канален двоен канал на RCA конектор 2-канален единичен канал на зелен конектор. Линеен Нивел; Импеданс: 1 KΩ Аудио вход 1-канален двоен канал на 3,5 мм конектор 1-канален двоен канал на RCA конектор. Честота на дискретизация: 48 KHz 6-канален единичен канал на зелен конектор. Честота на дискретизация: 48 KHz Честота на аудио дискретизация 48 KHz Декодиране Синхронно възпроизвеждане 1-гл Двоен поток поддържа | D13: друго | E13: 2 | F13: 4100 | G13: =E13*F13 -> 8200 | H13: =G13*1.2 -> 9840 | I13: оферта №1 Тех Смарт ЕООД 18.08.2023 и №4 от 13.08.23г.
A14: 11 | B14: камери | C14: 3840 x 2160 Резолюция при 30 кадъра в секунда IR осветление до 98' 2.8-12mm варифокален обектив 112,3 до 41,2° хоризонтално зрително поле Двупосочно аудио microSD слот поддържа до 256GB Ethernet порт с технология IK10-номинална вандалска устойчивост | D14: друго | E14: 2 | F14: 1171.58 | G14: =E14*F14 -> 2343.16 | H14: =G14*1.2 -> 2811.792 | I14: https://www.bhphotovideo.com/c/product/1702838-REG/hikvision_ids_2cd7186g0_izs_2_812_mm_deepinview_ids_2cd7186g0_izs_8mp_network.html 1049.39 лв https://www.networkcamerastore.com/hikvision-ids-2cd7186g0-izs-8-32mm-8mp-deepinview-m-vf-in-o-dome/ 1762.4 лв
A15: 12 | B15: камери | C15: Висококачествени изображения с 8 МР резолюция Отлична производителност при слаба светлина Ефективна технология за компресиране +, за да спести честотна лента и съхранение Ясни изображения срещу силна задна светлина благодарение на 120 dB истинска WDR технология 5 потока, за да отговарят на голямо разнообразие от приложения Вандал доказателство (IK10) | D15: друго | E15: 2 | F15: 1171.58 | G15: =E15*F15 -> 2343.16 | H15: =G15*1.2 -> 2811.792 | I15: https://www.networkcamerastore.com/hikvision-ids-2cd7186g0-izs-8-32mm-8mp-deepinview-m-vf-in-o-dome/ 1762.40 лв https://www.bhphotovideo.com/c/product/1702838-REG/hikvision_ids_2cd7186g0_izs_2_812_mm_deepinview_ids_2cd7186g0_izs_8mp_network.html 1049.39лв
... A20: 17 | B20: мултифункционално устройство | C20: Поддържан формат на хартията до SRA3 Стандартна памет от 8 GB RAM 25 ppm, за да бъдете в крак с нарастващото натоварване Капацитет на зареждане с хартията до 6 650 листа Скорост при цветно сканиране до 200 ipmПълна интеграция със система за управление на печата | D20: принтер | E20: 1 | F20: 5417.5 | G20: =E20*F20 -> 5417.5 | H20: =G20*1.2 -> 6501 | I20: https://mpsbulgaria.com/produkti/harduer/multifunkcionalni-ustroystva/konica-minolta-bizhub-c250i-multifunkcionalno-ustroystvo.html https://dilex.bg/pechat/kopirni-mashini/cveten-pechat/konica-minolta-bizhub-c250i-nov-model-sra3-cvetna-kopirna-mashina.osnovno-tyalo-cveten-kopir-cveten-skener-i-dvustranen-cveten-printer.300gr.hartiya.html
A21: 18 | E21: 0 | F21: 0 | G21: =E21*F21 -> 0 | H21: =G21*1.2 -> 0
A22: 19 | E22: 0 | F22: 0 | G22: =E22*F22 -> 0 | H22: =G22*1.2 -> 0
A23: 20 | E23: 0 | F23: 0 | G23: =E23*F23 -> 0 | H23: =G23*1.2 -> 0
A24: 21 | E24: 0 | F24: 0 | G24: =E24*F24 -> 0 | H24: =G24*1.2 -> 0
A25: 22 | E25: 0 | F25: 0 | G25: =E25*F25 -> 0 | H25: =G25*1.2 -> 0
A26: 23 | E26: 0 | F26: 0 | G26: =E26*F26 -> 0 | H26: =G26*1.2 -> 0
A27: 24 | E27: 0 | F27: 0 | G27: =E27*F27 -> 0 | H27: =G27*1.2 -> 0
A28: 25 | E28: 0 | F28: 0 | G28: =E28*F28 -> 0 | H28: =G28*1.2 -> 0
A29: 26 | E29: 0 | F29: 0 | G29: =E29*F29 -> 0 | H29: =G29*1.2 -> 0
A30: 27 | E30: 0 | F30: 0 | G30: =E30*F30 -> 0 | H30: =G30*1.2 -> 0
A31: 28 | E31: 0 | F31: 0 | G31: =E31*F31 -> 0 | H31: =G31*1.2 -> 0
A32: 29 | E32: 0 | F32: 0 | G32: =E32*F32 -> 0 | H32: =G32*1.2 -> 0
... A83: 80 | E83: 0 | F83: 0 | G83: =E83*F83 -> 0 | H83: =G83*1.2 -> 0
A84: Общо разходи за оборудване | G84: =SUM(G4:G83) -> 142080.78 | H84: =SUM(H4:H83) -> 170496.94
B85: Част II: Планиран за закупуване софтуер
A86: 1 | B86: Софтуер за редакция на изображения и графики | C86: професионален графичен софтуер, предназначен за обработка на изображения.Предлага богат набор от инструменти и функции, включително редактор за корекции на цветове, създаване на слоеве, ретуш и множество филтри, които подпомагат при създаването, редактирането и подобряването на графични проекти. | D86: х | E86: 27 | F86: 540 | G86: =E86*F86 -> 14580 | H86: =G86*1.2 -> 17496 | I86: https://www.adobe.com/bg/creativecloud/plans.html https://pixlr.com/pricing/
A87: 2 | B87: Софтуер за дигитализация на учебния процес | C87: Софтуер в подкрепа на дигиталната трансформация в образованието | D87: х | E87: 1 | F87: 5200 | G87: =E87*F87 -> 5200 | H87: =G87*1.2 -> 6240 | I87: Оферта 1 от 18.08.2023 и №6 31.07.23г.
A88: 3 | B88: софтуер за централизирано управление на интерактивни дисплеи | C88: софтуер за централизирано управление на дисплеи -Поддържани медийни формати: DAT, MPG, VOB, TS, AVI, MKV, MPS, MOV, 3GP, TS, FLV, WEBM, ASF, MP1, MP2, MP3, WMA, WAV, OGG, OGA, FLAC, ACC, M4A, XMF, MXMF, RTTTL, RTX, OTA, IMY, JPG, JPEG, BMP, GIF, PNG | D88: х | E88: 1 | F88: 5180 | G88: =E88*F88 -> 5180 | H88: =G88*1.2 -> 6216 | I88: Оферта 1 от 18.08.2023 и №6 31.07.23г.
A89: 4 | D89: х | E89: 0 | F89: 0 | G89: =E89*F89 -> 0 | H89: =G89*1.2 -> 0
A90: 5 | D90: х | E90: 0 | F90: 0 | G90: =E90*F90 -> 0 | H90: =G90*1.2 -> 0
A91: 6 | D91: х | E91: 0 | F91: 0 | G91: =E91*F91 -> 0 | H91: =G91*1.2 -> 0
A92: 7 | D92: х | E92: 0 | F92: 0 | G92: =E92*F92 -> 0 | H92: =G92*1.2 -> 0
A93: 8 | D93: х | E93: 0 | F93: 0 | G93: =E93*F93 -> 0 | H93: =G93*1.2 -> 0
A94: 9 | D94: х | E94: 0 | F94: 0 | G94: =E94*F94 -> 0 | H94: =G94*1.2 -> 0
A95: 10 | D95: х | E95: 0 | F95: 0 | G95: =E95*F95 -> 0 | H95: =G95*1.2 -> 0
A96: 11 | D96: х | E96: 0 | F96: 0 | G96: =E96*F96 -> 0 | H96: =G96*1.2 -> 0
A97: 12 | D97: х | E97: 0 | F97: 0 | G97: =E97*F97 -> 0 | H97: =G97*1.2 -> 0
A98: 13 | D98: х | E98: 0 | F98: 0 | G98: =E98*F98 -> 0 | H98: =G98*1.2 -> 0
A99: 14 | D99: х | E99: 0 | F99: 0 | G99: =E99*F99 -> 0 | H99: =G99*1.2 -> 0
A100: 15 | D100: х | E100: 0 | F100: 0 | G100: =E100*F100 -> 0 | H100: =G100*1.2 -> 0
... A125: 40 | D125: х | E125: 0 | F125: 0 | G125: =E125*F125 -> 0 | H125: =G125*1.2 -> 0
A126: Общо разходи за софтуер | G126: =SUM(G86:G125) -> 24960 | H126: =SUM(H86:H125) -> 29952
B127: Част III: Планирано за закупуване обзавеждане
A128: 1 | B128: Ученически чин 1 | C128: Модулна маса с трапецовидна форма. Дизайнът на масата позволява подредбата на няколко маси в различни конфигурации. Плот от ЛПДЧ 18 мм със заоблени ъгли, с ABS кантове с UV защита. Метална конструкция от прахово боядисана тръба с размери Ф20x1.5 мм. Размери: дължина 128.8 см, широчина 68 см, височина 54/60/64/ 68/72/76 см. | D128: х | E128: 52 | F128: 107.65 | G128: =E128*F128 -> 5597.8 | H128: =G128*1.2 -> 6717.36 | I128: https://mebelikan.bg/%D0%BF%D1%80%D0%BE%D0%B4%D1%83%D0%BA%D1%82%D0%B8/%D0%BC%D0%B0%D1%81%D0%B0-%D0%BC%D0%BE%D0%B4%D1%83%D0%BB%D0%BD%D0%B0-%D1%82%D1%80%D0%B0%D0%BF%D0%B5%D1%86%D0%BE%D0%B2%D0%B8%D0%B4%D0%BD%D0%B0?sector=schools https://uchmag.com/bg-bg/category/product/masa-modulna-trapetsovidna-s-metalni-kraka-129h68-n-54-300052694540759005/
A129: 2 | B129: Ученически чин 2 | C129: Модулна маса Кръг. Плотът е изработена от ЛПДЧ 18 мм с ABS кантове с UV защита. Ламинираното покритие позволява лесно почистване и поддържане. Конструкцията е с четири прахово боядисани крака Роси, изработени от стоманена тръба Ф50х1.5 мм. Размери: диаметър 80 см, височина 54/60/64/68/70/72/76 см | D129: х | E129: 4 | F129: 116.85 | G129: =E129*F129 -> 467.4 | H129: =G129*1.2 -> 560.88 | I129: https://mebelikan.bg/%D0%BF%D1%80%D0%BE%D0%B4%D1%83%D0%BA%D1%82%D0%B8/%D0%BC%D0%B0%D1%81%D0%B0-%D0%BC%D0%BE%D0%B4%D1%83%D0%BB%D0%BD%D0%B0-%D1%86%D0%B2%D0%B5%D1%82%D0%B5-%D0%BA%D1%80%D1%8A%D0%B3 https://uchmag.com/bg-bg/category/product/masa-modulna-tsvete-krag-f-80-n-70-300052694540747641/
A130: 3 | B130: Ученически стол 1 | C130: Ученически стол със заоблени ръбове, ергономична моноблок седалка и облегалка от пластмаса с височина 45 см. | D130: х | E130: 34 | F130: 89.9 | G130: =E130*F130 -> 3056.6 | H130: =G130*1.2 -> 3667.92 | I130: https://mebelikan.bg/%D0%BF%D1%80%D0%BE%D0%B4%D1%83%D0%BA%D1%82%D0%B8/%D1%81%D1%82%D0%BE%D0%BB-%D0%BC%D0%B0%D0%BA%D1%81%D0%B8%D0%BC%D0%B0-%D0%B0 https://www.toytown.bg/uchenicheski-stol-maxima-a-43-h-45-h-46-cm-krusha.html
A131: 4 | B131: Ученически стол 3 | C131: Ергономична моноблок седалка и облегалка от пластмаса. Облегалка с отвор за удобен захват и допълнителни две извивки за удобно окачване на раници. Височина 45 см. | D131: х | E131: 34 | F131: 56.9 | G131: =E131*F131 -> 1934.6 | H131: =G131*1.2 -> 2321.52 | I131: https://mebelikan.bg/%D0%BF%D1%80%D0%BE%D0%B4%D1%83%D0%BA%D1%82%D0%B8/%D1%81%D1%82%D0%BE%D0%BB-%D1%83%D1%87%D0%B5%D0%BD%D0%B8%D1%87%D0%B5%D1%81%D0%BA%D0%B8-%D0%BA%D1%8E%D1%82 https://www.toytown.bg/uchenicheski-stol-cute-430-h-425-h-460-mm-sin-ot-viii-do-xii-klas.html
A132: 5 | B132: Стол за висока маса | C132: Седалищна част - въртяща се и с твърда основа. Облегална част - твърда основа. Конструкция - метален крак, регулиреума височина. Дамаска - еко кожа. | D132: х | E132: 4 | F132: 132.5 | G132: =E132*F132 -> 530 | H132: =G132*1.2 -> 636 | I132: https://moemax.bg/product-11111111803289 https://jysk.bg/trapezariya/bar-masi/stolove/bar-stol-grindsted-kadife-sivo/cherno
A133: 6 | B133: Учителско бюро с помощен шкаф | C133: Бюрото с модерен дизайн. Помощният шкаф е с врата и 3 чекмеджета с централно заключване. Плотът е изработен от ЛПДЧ 18 мм с ABS кантове с UV защита. Конструкция: метал с Т-образен крак от прахово боядисана стоманена тръба Ф38х1.5 мм, с основа от тръба 50х30х1.5 мм. Декоративен елемент от перфорирана ламарина. PVC регулируеми стъпки. Размери: дължина 120 см, широчина 138.5 см, височина 75 см | D133: х | E133: 2 | F133: 394.15 | G133: =E133*F133 -> 788.3 | H133: =G133*1.2 -> 945.96 | I133: https://mebelikan.bg/%D0%BF%D1%80%D0%BE%D0%B4%D1%83%D0%BA%D1%82%D0%B8/%D0%B1%D1%8E%D1%80%D0%BE-%D0%BF%D0%BE%D0%BC%D0%BE%D1%89%D0%B5%D0%BD-%D1%88%D0%BA%D0%B0%D1%84-%D0%BC%D0%B0%D1%81%D0%B0 https://uchmag.com/bg-bg/category/product/byuro-uchitelsko-dyasno-sas-zaklyuchvane-118h65-n-76-300052694540759067/
A134: 7 | B134: Учителски стол | C134: Офис въртящ се стол с колелца и подлакътници | D134: х | E134: 2 | F134: 140.82 | G134: =E134*F134 -> 281.64 | H134: =G134*1.2 -> 337.968 | I134: https://mebelikan.bg/%D0%BF%D1%80%D0%BE%D0%B4%D1%83%D0%BA%D1%82%D0%B8/%D1%80%D0%B0%D0%B1%D0%BE%D1%82%D0%B5%D0%BD-%D1%81%D1%82%D0%BE%D0%BB-monti https://stem1.bg/product/rfg-raboten-stol-smart-w-damaska-i-mesh-cherna-sedalka-cherna-oblegalka
A135: 8 | B135: Демонстрационна маса /маса за роботи | C135: Изработена от ЛПДЧ 18 мм с ABS кантове с UV защита. С четири прахово боядисани крака Роси, изработени от стоманена тръба Ф50х1.5 мм. Размери: дължина 150/200 см, широчина 90 см, височина 80 см | D135: х | E135: 2 | F135: 392.8 | G135: =E135*F135 -> 785.6 | H135: =G135*1.2 -> 942.72 | I135: https://mebelikan.bg/%D0%BF%D1%80%D0%BE%D0%B4%D1%83%D0%BA%D1%82%D0%B8/%D0%BC%D0%B0%D1%81%D0%B0-%D0%B7%D0%B0%D1%81%D0%B5%D0%B4%D0%B0%D1%82%D0%B5%D0%BB%D0%BD%D0%B0-%D0%B0%D1%82%D0%B8%D0%BD%D0%B0 https://uchmag.com/bg-bg/category/product/masa-zasedatelna-atina-240h100-n-76-0-25-300052694540759033/
A136: 9 | B136: Висока маса Чичи | C136: Висока маса Чичи 169Х40 Н=100см | D136: х | E136: 2 | F136: 240.83 | G136: =E136*F136 -> 481.66 | H136: =G136*1.2 -> 577.992 | I136: https://www.ikea.bg/products/tommaryd-masa/29304826 https://aiko-bg.com/product-78453040002
A137: 10 | B137: Г-образна маса | C137: Съчетание от здрава метална конструкция и ламинирани плоскости. Плотът и подплотната са изработени от ЛПДЧ 18 мм с ABS кантове с UV защита. Конструкцията е с два Т-образни крака от прахово боядисана стоманена тръба Ф38х1.5 мм, с основа от тръба 50х30х1.5 мм. Декоративен елемент от перфорирана ламарина. PVC регулируеми стъпки. боядисана стоманена тръба Ф38х1.5 мм, с основа от тръба 50х30х1.5 мм. Декоративен елемент от перфорирана ламарина. PVC регулируеми стъпки. Размери: дължина 140 см, широчина 130 см, височина 75 см | D137: х | E137: 1 | F137: 304.8 | G137: =E137*F137 -> 304.8 | H137: =G137*1.2 -> 365.76 | I137: https://mebelikan.bg/%D0%BF%D1%80%D0%BE%D0%B4%D1%83%D0%BA%D1%82%D0%B8/%D0%BC%D0%B0%D1%81%D0%B0-%D0%B3-%D0%BE%D0%B1%D1%80%D0%B0%D0%B7%D0%BD%D0%B0 https://www.aliexpress.com/item/1005005465356172.html?spm=a2g0o.productlist.main.7.4f927b1eKF0HSk&algo_pvid=53db55ae-aed2-4c88-a3e7-6b7860e7f66f&algo_exp_id=53db55ae-aed2-4c88-a3e7-6b7860e7f66f-3&pdp_npi=4%40dis%21BGN%21677.58%21677.58%21%21%21369.78%21%21%402101d8f416926065593156377eb025%2112000033193048853%21sea%21BG%210%21A&curPageLogUid=OdyWjDvA6Ivq
A138: 11 | B138: Работна маса | C138: Изчистен дизайн. Масивният плот от ЛПДЧ 25 мм с ABS кантове с UV защита я прави изключително здрава и устойчива. Конструкцията е с два Т-образни крака от прахово боядисана стоманена тръба Ф38х1.5 мм, с основа от тръба 50х30х1.5 мм. Декоративен елемент от перфорирана ламарина. PVC регулируеми стъпки. Размери: дължина 180 см, широчина 70 см, височина 76 см | D138: х | E138: 1 | F138: 290.85 | G138: =E138*F138 -> 290.85 | H138: =G138*1.2 -> 349.02 | I138: https://mebelikan.bg/%D0%BF%D1%80%D0%BE%D0%B4%D1%83%D0%BA%D1%82%D0%B8/%D0%BC%D0%B0%D1%81%D0%B0-%D0%BA%D0%BE%D0%BD%D1%84%D0%B5%D1%80%D0%B5%D0%BD%D1%82%D0%BD%D0%B0-%D1%81%D0%BB%D0%B8%D0%B2%D0%B5%D0%BD-%D0%BF%D1%80%D0%B0%D0%B2%D0%B0 https://uchmag.com/bg-bg/category/product/masa-konferentna-sliven-prava-180h70-n-76-0-25-300052694540759031/
A139: 12 | B139: Модулна маса Полукръг | C139: Изчистен дизайн. Масивният плот от ЛПДЧ 25 мм с ABS кантове с UV защита я прави изключително здрава и устойчива. Конструкцията е с четири прахово боядисани крака Роси, изработени от стоманена тръба Ф50х1.5 мм. Размери: диаметър 140 см, широчина 70 см, височина 76 см | D139: х | E139: 2 | F139: 139 | G139: =E139*F139 -> 278 | H139: =G139*1.2 -> 333.6 | I139: https://mebelikan.bg/%D0%BF%D1%80%D0%BE%D0%B4%D1%83%D0%BA%D1%82%D0%B8/%D0%BC%D0%B0%D1%81%D0%B0-%D0%BA%D0%BE%D0%BD%D1%84%D0%B5%D1%80%D0%B5%D0%BD%D1%82%D0%BD%D0%B0-%D1%81%D0%BB%D0%B8%D0%B2%D0%B5%D0%BD-%D0%BF%D0%BE%D0%BB%D1%83%D0%BA%D1%80%D1%8A%D0%B3 https://uchitel.bg/uchenicheska-masa-rondo-polukrag-120h60sm-n71sm
... A156: 29 | B156: Секция Пчелна пита | C156: Секция Пчелна пита е изработена изцяло от ЛПДЧ 18 мм с ABS кантове с UV защита. Разполага с отворени и затворени модули и ниши във формата на шестоъгълник, имитиращи пчелна пита. Високите крайни шкафове са със заключване. С място за прибиране на табуретки Шестоъгълник, които се поръчват допълнително. Размери: широчина 675 см, дълбочина 45 см, височина 215 см | D156: х | E156: 1 | F156: 3337.15 | G156: =E156*F156 -> 3337.15 | H156: =G156*1.2 -> 4004.58 | I156: https://mebelikan.bg/%D0%BF%D1%80%D0%BE%D0%B4%D1%83%D0%BA%D1%82%D0%B8/%D1%81%D0%B5%D0%BA%D1%86%D0%B8%D1%8F-%D0%BF%D1%87%D0%B5%D0%BB%D0%BD%D0%B0-%D0%BF%D0%B8%D1%82%D0%B0 https://mipa-bg.com/product/%D0%B1%D0%B8%D0%BE-%D1%81%D1%82%D0%B5%D0%BB%D0%B0%D0%B6-%D0%BF%D1%87%D0%B5%D0%BB%D0%BD%D0%B0-%D0%BF%D0%B8%D1%82%D0%B0/
A157: 30 | D157: х | E157: 0 | F157: 0 | G157: =E157*F157 -> 0 | H157: =G157*1.2 -> 0
A158: 31 | D158: х | E158: 0 | F158: 0 | G158: =E158*F158 -> 0 | H158: =G158*1.2 -> 0
A159: 32 | D159: х | E159: 0 | F159: 0 | G159: =E159*F159 -> 0 | H159: =G159*1.2 -> 0
A160: 33 | D160: х | E160: 0 | F160: 0 | G160: =E160*F160 -> 0 | H160: =G160*1.2 -> 0
A161: 34 | D161: х | E161: 0 | F161: 0 | G161: =E161*F161 -> 0 | H161: =G161*1.2 -> 0
A162: 35 | D162: х | E162: 0 | F162: 0 | G162: =E162*F162 -> 0 | H162: =G162*1.2 -> 0
A163: 36 | D163: х | E163: 0 | F163: 0 | G163: =E163*F163 -> 0 | H163: =G163*1.2 -> 0
A164: 37 | D164: х | E164: 0 | F164: 0 | G164: =E164*F164 -> 0 | H164: =G164*1.2 -> 0
A165: 38 | D165: х | E165: 0 | F165: 0 | G165: =E165*F165 -> 0 | H165: =G165*1.2 -> 0
A166: 39 | D166: х | E166: 0 | F166: 0 | G166: =E166*F166 -> 0 | H166: =G166*1.2 -> 0
A167: 40 | D167: х | E167: 0 | F167: 0 | G167: =E167*F167 -> 0 | H167: =G167*1.2 -> 0
A168: 41 | D168: х | E168: 0 | F168: 0 | G168: =E168*F168 -> 0 | H168: =G168*1.2 -> 0
... A207: 80 | D207: х | E207: 0 | F207: 0 | G207: =E207*F207 -> 0 | H207: =G207*1.2 -> 0
A208: Общо разходи за обзавеждане | G208: =SUM(G128:G207) -> 32704.57 | H208: =SUM(H128:H207) -> 39245.484
A209: Част IV: Разходи за СМР
A210: 1 | D210: х | E210: 1 | F210: 49900.87 | G210: =E210*F210 -> 49900.87 | H210: =G210*1.2 -> 59881.044 | I210: -
A211: Общо разходи за СМР | G211: =SUM(G210:G210) -> 49900.87 | H211: =SUM(H210:H210) -> 59881.044
A212: Общо разходи за оборудване/обзавеждане/софтуер/СМР | G212: =G84+G126+G208+G211 -> 249646.22 | H212: =H84+H126+H208+H211 -> 299575.46
A213: ** В колона "Източник за формиране на единична цена на вид оборудване/софтуер/обзавеждане" се посочват подходящи източници на информация, въз основа на които са определени планираните стойности на разходите - проучвания в интернет (хиперлинкове към съответните интернет базирани източници) и/или номер и дата на оферта/и . ***С оглед коректното изчисляване на размера на исканото финансиране за изграждане на училищна STEM среда в част IV. Разходи за СМР, те се посочват общо, без да е необходимо тяхното описание, и за тях не се посочва източник за формиране на единична цена.

Sheet ВОСКС
A1: Остойностен списък с оборудване/софтуер за високотехнологични оборудвани и свързани класни стаи
A2: № по ред | B2: Наименование на оборудване/софтуер/СМР | C2: Описание/Технически спецификации/характеристики | D2: Минимално ниво на оборудването по Направлението | E2: Количество | F2: Единична цена без ДДС (лева) | G2: Общо без ДДС (лева) | H2: Общо с ДДС (лева) | I2: Източник за формиране на единична цена на вид оборудване/софтуер/обзавеждане**
A3: Част I: Планирано за закупуване оборудване
A4: 1 | B4: Интерактивен дисплей с широкоъгълна камера и микрофон | C4: 65-инчов 4K интерактивен плосък панел с камера и микрофон, с OPS/OPS-C устройства, реализирайки плавно превключване между вградените системи. | D4: интерактивен дисплей с вграден компютърен OPS модул и вградена точка за достъп с интегрирана широкоъгълна камера и микрофон | E4: 6 | F4: 6185 | G4: =E4*F4 -> 37110 | H4: =G4*1.2 -> 44532 | I4: https://ont.bg/bg-product-details-158.html - 6048 лв с ддс https://www.jmt.bg/newline-tt-6522z-pid78504 - 8897 лв с ддс
A5: 2 | B5: преносим компютър | C5: Процесор: 3.30 GHz, 10 MB cache Памет: 8GB 3200GHz DDR4 Диск: SSD 512GB Дисплей: 15.6'' , 1920x1080 dpi Мрежа: 10/100/1000 Mbps Безжична мрежа: 802.11ac 1x1 WiFi, Bluetooth Портове, 1 х USB 3.2 Gen 1, 1 х USB 2.0, 1 х HDMI Web камера: HD cam Кирилизация БДС кирилизация на клавиатурата Инсталирана операционна система | D5: преносим компютър | E5: 6 | F5: 1232.5 | G5: =E5*F5 -> 7395 | H5: =G5*1.2 -> 8874 | I5: https://www.ozone.bg/product/laptop-dell-vostro-3530-intel-core-5-1335u-12-mb-cache-up-to-4-60-ghz-15-6-fhd-1920x1080-ag-120hz-wva-250nits-8gb-1x8gb-ddr4-512gb-pcie-m-2-uhd-graphics-hd-cam-and-mic-802-11ac-bg-kb-win-11-pro-3y-bos/ - 1699 лв с ДДС https://ardes.bg/product/dell-vostro-3520-n1614pvnb3520emea01-ubu-16gb-w11h-317367 - 1178 лв с ддс
A6: 3 | E6: 0 | F6: 0 | G6: =E6*F6 -> 0 | H6: =G6*1.2 -> 0
A7: 4 | E7: 0 | F7: 0 | G7: =E7*F7 -> 0 | H7: =G7*1.2 -> 0
A8: 5 | E8: 0 | F8: 0 | G8: =E8*F8 -> 0 | H8: =G8*1.2 -> 0
A9: 6 | E9: 0 | F9: 0 | G9: =E9*F9 -> 0 | H9: =G9*1.2 -> 0
A10: 7 | E10: 0 | F10: 0 | G10: =E10*F10 -> 0 | H10: =G10*1.2 -> 0
A11: 8 | E11: 0 | F11: 0 | G11: =E11*F11 -> 0 | H11: =G11*1.2 -> 0
A12: 9 | E12: 0 | F12: 0 | G12: =E12*F12 -> 0 | H12: =G12*1.2 -> 0
A13: 10 | E13: 0 | F13: 0 | G13: =E13*F13 -> 0 | H13: =G13*1.2 -> 0
A14: 11 | E14: 0 | F14: 0 | G14: =E14*F14 -> 0 | H14: =G14*1.2 -> 0
A15: 12 | E15: 0 | F15: 0 | G15: =E15*F15 -> 0 | H15: =G15*1.2 -> 0
A16: 13 | E16: 0 | F16: 0 | G16: =E16*F16 -> 0 | H16: =G16*1.2 -> 0
A17: 14 | E17: 0 | F17: 0 | G17: =E17*F17 -> 0 | H17: =G17*1.2 -> 0
... A43: 40 | E43: 0 | F43: 0 | G43: =E43*F43 -> 0 | H43: =G43*1.2 -> 0
A44: =A43+1 -> 41 | E44: 0 | F44: 0 | G44: =E44*F44 -> 0 | H44: =G44*1.2 -> 0
A45: =A44+1 -> 42 | E45: 0 | F45: 0 | G45: =E45*F45 -> 0 | H45: =G45*1.2 -> 0
A46: =A45+1 -> 43 | E46: 0 | F46: 0 | G46: =E46*F46 -> 0 | H46: =G46*1.2 -> 0
A47: =A46+1 -> 44 | E47: 0 | F47: 0 | G47: =E47*F47 -> 0 | H47: =G47*1.2 -> 0
A48: =A47+1 -> 45 | E48: 0 | F48: 0 | G48: =E48*F48 -> 0 | H48: =G48*1.2 -> 0
A49: =A48+1 -> 46 | E49: 0 | F49: 0 | G49: =E49*F49 -> 0 | H49: =G49*1.2 -> 0
A50: =A49+1 -> 47 | E50: 0 | F50: 0 | G50: =E50*F50 -> 0 | H50: =G50*1.2 -> 0
A51: =A50+1 -> 48 | E51: 0 | F51: 0 | G51: =E51*F51 -> 0 | H51: =G51*1.2 -> 0
A52: =A51+1 -> 49 | E52: 0 | F52: 0 | G52: =E52*F52 -> 0 | H52: =G52*1.2 -> 0
A53: =A52+1 -> 50 | E53: 0 | F53: 0 | G53: =E53*F53 -> 0 | H53: =G53*1.2 -> 0
A54: =A53+1 -> 51 | E54: 0 | F54: 0 | G54: =E54*F54 -> 0 | H54: =G54*1.2 -> 0
A55: =A54+1 -> 52 | E55: 0 | F55: 0 | G55: =E55*F55 -> 0 | H55: =G55*1.2 -> 0
... A83: =A82+1 -> 80 | E83: 0 | F83: 0 | G83: =E83*F83 -> 0 | H83: =G83*1.2 -> 0
A84: Общо разходи за оборудване | G84: =SUM(G4:G83) -> 44505 | H84: =SUM(H4:H83) -> 53406
B85: Част II: Планиран за закупуване софтуер
A86: 1 | B86: софтуер за управление на дигитално съдържание | C86: Създаване на програми и плейлисти Управление на списъци с програми и preview Връзка с всички терминали/екрани в мрежата, преглед на статуса им и съдържанието Създаване на разписания и графици Въвеждане на текстови съобщения | D86: х | E86: 6 | F86: 820 | G86: =E86*F86 -> 4920 | H86: =G86*1.2 -> 5904 | I86: Оферта 1 от 18.08.2023 и №6 31.07.23г.
A87: 2 | D87: х | E87: 0 | F87: 0 | G87: =E87*F87 -> 0 | H87: =G87*1.2 -> 0
A88: 3 | D88: х | E88: 0 | F88: 0 | G88: =E88*F88 -> 0 | H88: =G88*1.2 -> 0
A89: 4 | D89: х | E89: 0 | F89: 0 | G89: =E89*F89 -> 0 | H89: =G89*1.2 -> 0
A90: 5 | D90: х | E90: 0 | F90: 0 | G90: =E90*F90 -> 0 | H90: =G90*1.2 -> 0
A91: 6 | D91: х | E91: 0 | F91: 0 | G91: =E91*F91 -> 0 | H91: =G91*1.2 -> 0
A92: 7 | D92: х | E92: 0 | F92: 0 | G92: =E92*F92 -> 0 | H92: =G92*1.2 -> 0
A93: 8 | D93: х | E93: 0 | F93: 0 | G93: =E93*F93 -> 0 | H93: =G93*1.2 -> 0
A94: 9 | D94: х | E94: 0 | F94: 0 | G94: =E94*F94 -> 0 | H94: =G94*1.2 -> 0
A95: 10 | D95: х | E95: 0 | F95: 0 | G95: =E95*F95 -> 0 | H95: =G95*1.2 -> 0
A96: 11 | D96: х | E96: 0 | F96: 0 | G96: =E96*F96 -> 0 | H96: =G96*1.2 -> 0
A97: 12 | D97: х | E97: 0 | F97: 0 | G97: =E97*F97 -> 0 | H97: =G97*1.2 -> 0
A98: 13 | D98: х | E98: 0 | F98: 0 | G98: =E98*F98 -> 0 | H98: =G98*1.2 -> 0
... A125: 40 | D125: х | E125: 0 | F125: 0 | G125: =E125*F125 -> 0 | H125: =G125*1.2 -> 0
A126: Общо разходи за софтуер | G126: =SUM(G86:G125) -> 4920 | H126: =SUM(H86:H125) -> 5904
A127: Общо разходи за оборудване/софтуер | G127: =G84+G126 -> 49425 | H127: =H84+H126 -> 59310
A128: ** В колона "Източник за формиране на единична цена на вид оборудване/софтуер" се посочват подходящи източници на информация, въз основа на които са определени планираните стойности на разходите - проучвания в интернет (хиперлинкове към съответните интернет базирани източници) и/или номер и дата на оферта/и.

Sheet Специализирано оборудване
A1: Остойностен списък със специализирано оборудване/софтуер
A2: № по ред | B2: Наименование на оборудване/софтуер/СМР | C2: Описание/Технически спецификации/характеристики | D2: Минимално ниво на оборудването по Направлението | E2: Количество | F2: Единична цена без ДДС (лева) | G2: Общо без ДДС (лева) | H2: Общо с ДДС (лева) | I2: Източник за формиране на единична цена на вид оборудване/софтуер/обзавеждане**
A3: Част I: Планирано за закупуване оборудване
A4: 1 | E4: 0 | F4: 0 | G4: =E4*F4 -> 0 | H4: =G4*1.2 -> 0
A5: 2 | E5: 0 | F5: 0 | G5: =E5*F5 -> 0 | H5: =G5*1.2 -> 0
A6: 3 | E6: 0 | F6: 0 | G6: =E6*F6 -> 0 | H6: =G6*1.2 -> 0
A7: 4 | E7: 0 | F7: 0 | G7: =E7*F7 -> 0 | H7: =G7*1.2 -> 0
A8: 5 | E8: 0 | F8: 0 | G8: =E8*F8 -> 0 | H8: =G8*1.2 -> 0
A9: 6 | E9: 0 | F9: 0 | G9: =E9*F9 -> 0 | H9: =G9*1.2 -> 0
A10: 7 | E10: 0 | F10: 0 | G10: =E10*F10 -> 0 | H10: =G10*1.2 -> 0
A11: 8 | E11: 0 | F11: 0 | G11: =E11*F11 -> 0 | H11: =G11*1.2 -> 0
A12: 9 | E12: 0 | F12: 0 | G12: =E12*F12 -> 0 | H12: =G12*1.2 -> 0
A13: 10 | E13: 0 | F13: 0 | G13: =E13*F13 -> 0 | H13: =G13*1.2 -> 0
A14: 11 | E14: 0 | F14: 0 | G14: =E14*F14 -> 0 | H14: =G14*1.2 -> 0
A15: 12 | E15: 0 | F15: 0 | G15: =E15*F15 -> 0 | H15: =G15*1.2 -> 0
... A83: 80 | E83: 0 | F83: 0 | G83: =E83*F83 -> 0 | H83: =G83*1.2 -> 0
A84: Общо разходи за оборудване | G84: =SUM(G4:G43) -> 0 | H84: =SUM(H4:H43) -> 0
B85: Част II: Планиран за закупуване софтуер
A86: 1 | D86: х | E86: 0 | F86: 0 | G86: =E86*F86 -> 0 | H86: =G86*1.2 -> 0
A87: 2 | D87: х | E87: 0 | F87: 0 | G87: =E87*F87 -> 0 | H87: =G87*1.2 -> 0
A88: 3 | D88: х | E88: 0 | F88: 0 | G88: =E88*F88 -> 0 | H88: =G88*1.2 -> 0
A89: 4 | D89: х | E89: 0 | F89: 0 | G89: =E89*F89 -> 0 | H89: =G89*1.2 -> 0
A90: 5 | D90: х | E90: 0 | F90: 0 | G90: =E90*F90 -> 0 | H90: =G90*1.2 -> 0
A91: 6 | D91: х | E91: 0 | F91: 0 | G91: =E91*F91 -> 0 | H91: =G91*1.2 -> 0
A92: 7 | D92: х | E92: 0 | F92: 0 | G92: =E92*F92 -> 0 | H92: =G92*1.2 -> 0
A93: 8 | D93: х | E93: 0 | F93: 0 | G93: =E93*F93 -> 0 | H93: =G93*1.2 -> 0
A94: 9 | D94: х | E94: 0 | F94: 0 | G94: =E94*F94 -> 0 | H94: =G94*1.2 -> 0
A95: 10 | D95: х | E95: 0 | F95: 0 | G95: =E95*F95 -> 0 | H95: =G95*1.2 -> 0
A96: 11 | D96: х | E96: 0 | F96: 0 | G96: =E96*F96 -> 0 | H96: =G96*1.2 -> 0
A97: 12 | D97: х | E97: 0 | F97: 0 | G97: =E97*F97 -> 0 | H97: =G97*1.2 -> 0
... A125: 40 | D125: х | E125: 0 | F125: 0 | G125: =E125*F125 -> 0 | H125: =G125*1.2 -> 0
A126: Общо разходи за софтуер | G126: =SUM(G86:G105) -> 0 | H126: =SUM(H86:H105) -> 0
A127: Общо разходи за оборудване/софтуер | G127: =G84+G126 -> 0 | H127: =H84+H126 -> 0
A128: ** В колона "Източник за формиране на единична цена на вид оборудване/софтуер" се посочват подходящи източници на информация, въз основа на които са определени планираните стойности на разходите - проучвания в интернет (хиперлинкове към съответните интернет базирани източници) и/или номер и дата на оферта/и.

Sheet Училища
A1: Код по НЕИСПУО | B1: Област | C1: Община | D1: Населено място | E1: Пълно наименование на институция | F1: Детайлен вид на институция | G1: Вид на институцията според финансирането | H1: Учебна 2020/2021 година | I1: Учебна 2021/2022 година | J1: Учебна 2022/2023 година | K1: Средноаритметичен брой ученици за учебните 2020/2021, 2021/2022 и 2022/2023 учебна година | L1: Средства STEM в лв. с ДДС | M1: в това число максимален размер на разходите за СМР и обзавеждане за STEM (до 45 % от средствата за STEM) в лв. с ДДС | N1: в това число минимален размер на разходите за оборудване за STEM (минимум 45 % от средствата за STEM) в лв. с ДДС | O1: в това число максимален размер на разходите за допълнително специализирано оборудване за STEM (до 20 % от разходите за оборудване за STEM) в лв. с ДДС | P1: в това число максимален размер на разходите за софтуер за STEM (до 10 % от средствата за STEM) в лв. с ДДС | Q1: Средства ВОСКС в лв. с ДДС | R1: Минимален брой оборудвани ВОСКС | S1: в това число максимален размер на разходите за софтуер за ВОСКС (до 10 % от средствата за ВОСКС) в лв. с ДДС | T1: Общо средства (STEM и ВОСКС) в лв. с ДДС | U1: Средства за организация и управление (1%) от средствата за STEM и ВОСКС в лв. с ДДС | V1: Общо средства за изграждане на училищна STEM среда в лв. с ДДС | W1: Булстат/ЕИК
A2: 1702623 | B2: Разград | C2: Разград | D2: Киченица | E2: Основно училище "Кирил и Методий" | F2: основно | G2: Общинско | H2: 39 | I2: 36 | J2: 15 | K2: =+(H2+I2+J2)/3 -> 30 | L2: 0 | M2: =+L2*0.45 -> 0 | N2: =+L2*0.45 -> 0 | O2: =+N2*0.2 -> 0 | P2: =++L2*0.1 -> 0 | Q2: 0 | R2: 0 | S2: =+Q2*0.1 -> 0 | T2: =+L2+Q2 -> 0 | U2: =+T2*0.01 -> 0 | V2: =+T2+U2 -> 0 | W2: 000498800
A3: 1900516 | B3: Силистра | C3: Силистра | D3: Брадвари | E3: Основно училище "Св. св. Кирил и Методий" | F3: основно | G3: Общинско | H3: 50 | I3: 39 | J3: 35 | K3: =+(H3+I3+J3)/3 -> 41.333333 | L3: 0 | M3: =+L3*0.45 -> 0 | N3: =+L3*0.45 -> 0 | O3: =+N3*0.2 -> 0 | P3: =++L3*0.1 -> 0 | Q3: 0 | R3: 0 | S3: =+Q3*0.1 -> 0 | T3: =+L3+Q3 -> 0 | U3: =+T3*0.01 -> 0 | V3: =+T3+U3 -> 0 | W3: 000558667
A4: 100020 | B4: Благоевград | C4: Благоевград | D4: Благоевград | E4: Второ основно училище "Димитър Благоев" | F4: основно | G4: Общинско | H4: 528 | I4: 531 | J4: 533 | K4: =+(H4+I4+J4)/3 -> 530.66667 | L4: =300000*0.7 -> 210000 | M4: =+L4*0.45 -> 94500 | N4: =+L4*0.45 -> 94500 | O4: =+N4*0.2 -> 18900 | P4: =++L4*0.1 -> 21000 | Q4: 60000 | R4: 6 | S4: =+Q4*0.1 -> 6000 | T4: =+L4+Q4 -> 270000 | U4: =+T4*0.01 -> 2700 | V4: =+T4+U4 -> 272700 | W4: 000012465
A5: 100040 | B5: Благоевград | C5: Благоевград | D5: Благоевград | E5: Четвърто основно училище " Димчо Дебелянов" | F5: основно | G5: Общинско | H5: 261 | I5: 271 | J5: 281 | K5: =+(H5+I5+J5)/3 -> 271 | L5: 200000 | M5: =+L5*0.45 -> 90000 | N5: =+L5*0.45 -> 90000 | O5: =+N5*0.2 -> 18000 | P5: =++L5*0.1 -> 20000 | Q5: 50000 | R5: 5 | S5: =+Q5*0.1 -> 5000 | T5: =+L5+Q5 -> 250000 | U5: =+T5*0.01 -> 2500 | V5: =+T5+U5 -> 252500 | W5: 000012487
A6: 100052 | B6: Благоевград | C6: Благоевград | D6: Благоевград | E6: Благоевградска професионална гимназия "Ичко Бойчев" | F6: професионална гимназия | G6: Общинско | H6: 253 | I6: 280 | J6: 298 | K6: =+(H6+I6+J6)/3 -> 277 | L6: 200000 | M6: =+L6*0.45 -> 90000 | N6: =+L6*0.45 -> 90000 | O6: =+N6*0.2 -> 18000 | P6: =++L6*0.1 -> 20000 | Q6: 50000 | R6: 5 | S6: =+Q6*0.1 -> 5000 | T6: =+L6+Q6 -> 250000 | U6: =+T6*0.01 -> 2500 | V6: =+T6+U6 -> 252500 | W6: 000017003
A7: 100070 | B7: Благоевград | C7: Благоевград | D7: Благоевград | E7: Седмо средно училище "Кузман Шапкарев" | F7: средно | G7: Общинско | H7: 888 | I7: 923 | J7: 923 | K7: =+(H7+I7+J7)/3 -> 911.33333 | L7: =300000*0.7 -> 210000 | M7: =+L7*0.45 -> 94500 | N7: =+L7*0.45 -> 94500 | O7: =+N7*0.2 -> 18900 | P7: =++L7*0.1 -> 21000 | Q7: 60000 | R7: 6 | S7: =+Q7*0.1 -> 6000 | T7: =+L7+Q7 -> 270000 | U7: =+T7*0.01 -> 2700 | V7: =+T7+U7 -> 272700 | W7: 000016976
A8: 100110 | B8: Благоевград | C8: Благоевград | D8: Благоевград | E8: Единадесето основно училище "Христо Ботев" | F8: основно | G8: Общинско | H8: 364 | I8: 385 | J8: 401 | K8: =+(H8+I8+J8)/3 -> 383.33333 | L8: 200000 | M8: =+L8*0.45 -> 90000 | N8: =+L8*0.45 -> 90000 | O8: =+N8*0.2 -> 18000 | P8: =++L8*0.1 -> 20000 | Q8: 50000 | R8: 5 | S8: =+Q8*0.1 -> 5000 | T8: =+L8+Q8 -> 250000 | U8: =+T8*0.01 -> 2500 | V8: =+T8+U8 -> 252500 | W8: 000019399
A9: 100190 | B9: Благоевград | C9: Благоевград | D9: Благоевград | E9: Езикова гимназия "Акад. Людмил Стоянов" | F9: профилирана гимназия | G9: Общинско | H9: 795 | I9: 793 | J9: 795 | K9: =+(H9+I9+J9)/3 -> 794.33333 | L9: =300000 -> 300000 | M9: =+L9*0.45 -> 135000 | N9: =+L9*0.45 -> 135000 | O9: =+N9*0.2 -> 27000 | P9: =++L9*0.1 -> 30000 | Q9: 60000 | R9: 6 | S9: =+Q9*0.1 -> 6000 | T9: =+L9+Q9 -> 360000 | U9: =+T9*0.01 -> 3600 | V9: =+T9+U9 -> 363600 | W9: 000019100
A10: 100200 | B10: Благоевград | C10: Благоевград | D10: Благоевград | E10: Природо-математическа гимназия "Акад. Сергей Корольов" | F10: профилирана гимназия | G10: Общинско | H10: 868 | I10: 866 | J10: 863 | K10: =+(H10+I10+J10)/3 -> 865.66667 | L10: =300000 -> 300000 | M10: =+L10*0.45 -> 135000 | N10: =+L10*0.45 -> 135000 | O10: =+N10*0.2 -> 27000 | P10: =++L10*0.1 -> 30000 | Q10: 60000 | R10: 6 | S10: =+Q10*0.1 -> 6000 | T10: =+L10+Q10 -> 360000 | U10: =+T10*0.01 -> 3600 | V10: =+T10+U10 -> 363600 | W10: 000016983
A11: 100280 | B11: Благоевград | C11: Благоевград | D11: Благоевград | E11: Професионална гимназия по икономика "Иван Илиев" | F11: професионална гимназия | G11: Държавно | H11: 545 | I11: 520 | J11: 518 | K11: =+(H11+I11+J11)/3 -> 527.66667 | L11: =300000 -> 300000 | M11: =+L11*0.45 -> 135000 | N11: =+L11*0.45 -> 135000 | O11: =+N11*0.2 -> 27000 | P11: =++L11*0.1 -> 30000 | Q11: 60000 | R11: 6 | S11: =+Q11*0.1 -> 6000 | T11: =+L11+Q11 -> 360000 | U11: =+T11*0.01 -> 3600 | V11: =+T11+U11 -> 363600 | W11: 000014060
A12: 100300 | B12: Благоевград | C12: Благоевград | D12: Благоевград | E12: Професионална гимназия по строителство, архитектура и геодезия " Васил Левски" | F12: професионална гимназия | G12: Държавно | H12: 389 | I12: 378 | J12: 401 | K12: =+(H12+I12+J12)/3 -> 389.33333 | L12: 200000 | M12: =+L12*0.45 -> 90000 | N12: =+L12*0.45 -> 90000 | O12: =+N12*0.2 -> 18000 | P12: =++L12*0.1 -> 20000 | Q12: 50000 | R12: 5 | S12: =+Q12*0.1 -> 5000 | T12: =+L12+Q12 -> 250000 | U12: =+T12*0.01 -> 2500 | V12: =+T12+U12 -> 252500 | W12: 000014078
A13: 101250 | B13: Благоевград | C13: Благоевград | D13: Благоевград | E13: Средно училище с изучаване на чужди езици "Свети Климент Охридски" | F13: средно | G13: Общинско | H13: 505 | I13: 469 | J13: 459 | K13: =+(H13+I13+J13)/3 -> 477.66667 | L13: =300000 -> 300000 | M13: =+L13*0.45 -> 135000 | N13: =+L13*0.45 -> 135000 | O13: =+N13*0.2 -> 27000 | P13: =++L13*0.1 -> 30000 | Q13: 60000 | R13: 6 | S13: =+Q13*0.1 -> 6000 | T13: =+L13+Q13 -> 360000 | U13: =+T13*0.01 -> 3600 | V13: =+T13+U13 -> 363600 | W13: 000019456
A14: 101290 | B14: Благоевград | C14: Благоевград | D14: Благоевград | E14: Трето основно училище "Димитър Талев" | F14: основно | G14: Общинско | H14: 782 | I14: 741 | J14: 695 | K14: =+(H14+I14+J14)/3 -> 739.33333 | L14: =300000 -> 300000 | M14: =+L14*0.45 -> 135000 | N14: =+L14*0.45 -> 135000 | O14: =+N14*0.2 -> 27000 | P14: =++L14*0.1 -> 30000 | Q14: 60000 | R14: 6 | S14: =+Q14*0.1 -> 6000 | T14: =+L14+Q14 -> 360000 | U14: =+T14*0.01 -> 3600 | V14: =+T14+U14 -> 363600 | W14: 000012472
A15: 101301 | B15: Благоевград | C15: Гърмен | D15: Гърмен | E15: Средно училище "Св.Св.Кирил и Методий" | F15: средно | G15: Общинско | H15: 348 | I15: 333 | J15: 319 | K15: =+(H15+I15+J15)/3 -> 333.33333 | L15: 200000 | M15: =+L15*0.45 -> 90000 | N15: =+L15*0.45 -> 90000 | O15: =+N15*0.2 -> 18000 | P15: =++L15*0.1 -> 20000 | Q15: 50000 | R15: 5 | S15: =+Q15*0.1 -> 5000 | T15: =+L15+Q15 -> 250000 | U15: =+T15*0.01 -> 2500 | V15: =+T15+U15 -> 252500 | W15: 000012942
A16: 101580 | B16: Благоевград | C16: Благоевград | D16: Благоевград | E16: Осмо средно училище "Арсени Костенцев" | F16: средно | G16: Общинско | H16: 716 | I16: 685 | J16: 676 | K16: =+(H16+I16+J16)/3 -> 692.33333 | L16: =300000 -> 300000 | M16: =+L16*0.45 -> 135000 | N16: =+L16*0.45 -> 135000 | O16: =+N16*0.2 -> 27000 | P16: =++L16*0.1 -> 30000 | Q16: 60000 | R16: 6 | S16: =+Q16*0.1 -> 6000 | T16: =+L16+Q16 -> 360000 | U16: =+T16*0.01 -> 3600 | V16: =+T16+U16 -> 363600 | W16: 000019050
A17: 101700 | B17: Благоевград | C17: Благоевград | D17: Благоевград | E17: Девето основно училище " Пейо Крачолов Яворов" | F17: основно | G17: Общинско | H17: 111 | I17: 105 | J17: 117 | K17: =+(H17+I17+J17)/3 -> 111 | L17: 150000 | M17: =+L17*0.45 -> 67500 | N17: =+L17*0.45 -> 67500 | O17: =+N17*0.2 -> 13500 | P17: =++L17*0.1 -> 15000 | Q17: 30000 | R17: 3 | S17: =+Q17*0.1 -> 3000 | T17: =+L17+Q17 -> 180000 | U17: =+T17*0.01 -> 1800 | V17: =+T17+U17 -> 181800 | W17: 000019189
A18: 101730 | B18: Благоевград | C18: Благоевград | D18: Благоевград | E18: Професионална гимназия по туризъм и лека промишленост "Гоце Делчев" | F18: професионална гимназия | G18: Общинско | H18: 200 | I18: 212 | J18: 230 | K18: =+(H18+I18+J18)/3 -> 214 | L18: 200000 | M18: =+L18*0.45 -> 90000 | N18: =+L18*0.45 -> 90000 | O18: =+N18*0.2 -> 18000 | P18: =++L18*0.1 -> 20000 | Q18: 50000 | R18: 5 | S18: =+Q18*0.1 -> 5000 | T18: =+L18+Q18 -> 250000 | U18: =+T18*0.01 -> 2500 | V18: =+T18+U18 -> 252500 | W18: 101074104
A19: 101820 | B19: Благоевград | C19: Благоевград | D19: Благоевград | E19: Център за специална образователна подкрепа "Свети Паисий Хилендарски" | F19: център за специална образователна подкрепа | G19: Държавно | H19: 109 | I19: 121 | J19: 121 | K19: =+(H19+I19+J19)/3 -> 117 | L19: 150000 | M19: =+L19*0.45 -> 67500 | N19: =+L19*0.45 -> 67500 | O19: =+N19*0.2 -> 13500 | P19: =++L19*0.1 -> 15000 | Q19: 30000 | R19: 3 | S19: =+Q19*0.1 -> 3000 | T19: =+L19+Q19 -> 180000 | U19: =+T19*0.01 -> 1800 | V19: =+T19+U19 -> 181800 | W19: 000014014
A20: 101870 | B20: Благоевград | C20: Благоевград | D20: Благоевград | E20: Национална хуманитарна гимназия"Св.св.Кирил и Методий" | F20: профилирана гимназия | G20: Общинско | H20: 620 | I20: 648 | J20: 666 | K20: =+(H20+I20+J20)/3 -> 644.66667 | L20: =300000 -> 300000 | M20: =+L20*0.45 -> 135000 | N20: =+L20*0.45 -> 135000 | O20: =+N20*0.2 -> 27000 | P20: =++L20*0.1 -> 30000 | Q20: 60000 | R20: 6 | S20: =+Q20*0.1 -> 6000 | T20: =+L20+Q20 -> 360000 | U20: =+T20*0.01 -> 3600 | V20: =+T20+U20 -> 363600 | W20: 000013916
A21: 101880 | B21: Благоевград | C21: Благоевград | D21: Благоевград | E21: Средно училище "Иван Вазов" | F21: средно | G21: Общинско | H21: 445 | I21: 452 | J21: 467 | K21: =+(H21+I21+J21)/3 -> 454.66667 | L21: =300000 -> 300000 | M21: =+L21*0.45 -> 135000 | N21: =+L21*0.45 -> 135000 | O21: =+N21*0.2 -> 27000 | P21: =++L21*0.1 -> 30000 | Q21: 60000 | R21: 6 | S21: =+Q21*0.1 -> 6000 | T21: =+L21+Q21 -> 360000 | U21: =+T21*0.01 -> 3600 | V21: =+T21+U21 -> 363600 | W21: 000012700
A22: 102001 | B22: Благоевград | C22: Гоце Делчев | D22: Гоце Делчев | E22: Неврокопска професионална гимназия "Димитър Талев" | F22: професионална гимназия | G22: Държавно | H22: 711 | I22: 770 | J22: 817 | K22: =+(H22+I22+J22)/3 -> 766 | L22: =300000 -> 300000 | M22: =+L22*0.45 -> 135000 | N22: =+L22*0.45 -> 135000 | O22: =+N22*0.2 -> 27000 | P22: =++L22*0.1 -> 30000 | Q22: 60000 | R22: 6 | S22: =+Q22*0.1 -> 6000 | T22: =+L22+Q22 -> 360000 | U22: =+T22*0.01 -> 3600 | V22: =+T22+U22 -> 363600 | W22: 000014249
A23: 102002 | B23: Благоевград | C23: Гоце Делчев | D23: Гоце Делчев | E23: Природо-математическа гимназия "Яне Сандански" | F23: профилирана гимназия | G23: Общинско | H23: 703 | I23: 717 | J23: 703 | K23: =+(H23+I23+J23)/3 -> 707.66667 | L23: =300000 -> 300000 | M23: =+L23*0.45 -> 135000 | N23: =+L23*0.45 -> 135000 | O23: =+N23*0.2 -> 27000 | P23: =++L23*0.1 -> 30000 | Q23: 60000 | R23: 6 | S23: =+Q23*0.1 -> 6000 | T23: =+L23+Q23 -> 360000 | U23: =+T23*0.01 -> 3600 | V23: =+T23+U23 -> 363600 | W23: 000013923
A24: 102003 | B24: Благоевград | C24: Банско | D24: Места | E24: Основно училище "Свети свети Кирил и Методий" | F24: основно | G24: Общинско | H24: 51 | I24: 51 | J24: 48 | K24: =+(H24+I24+J24)/3 -> 50 | L24: 50000 | M24: =+L24*0.45 -> 22500 | N24: =+L24*0.45 -> 22500 | O24: =+N24*0.2 -> 4500 | P24: =++L24*0.1 -> 5000 | Q24: 10000 | R24: 1 | S24: =+Q24*0.1 -> 1000 | T24: =+L24+Q24 -> 60000 | U24: =+T24*0.01 -> 600 | V24: =+T24+U24 -> 60600 | W24: 000013081
A25: 102004 | B25: Благоевград | C25: Банско | D25: Банско | E25: Професионална лесотехническа гимназия"Никола Йонков Вапцаров" | F25: професионална гимназия | G25: Общинско | H25: 193 | I25: 171 | J25: 159 | K25: =+(H25+I25+J25)/3 -> 174.33333 | L25: =150000*0.7 -> 105000 | M25: =+L25*0.45 -> 47250 | N25: =+L25*0.45 -> 47250 | O25: =+N25*0.2 -> 9450 | P25: =++L25*0.1 -> 10500 | Q25: 30000 | R25: 3 | S25: =+Q25*0.1 -> 3000 | T25: =+L25+Q25 -> 135000 | U25: =+T25*0.01 -> 1350 | V25: =+T25+U25 -> 136350 | W25: 000014103
A26: 102007 | B26: Благоевград | C26: Сандански | D26: Сандански | E26: Професионална техническа гимназия | F26: професионална гимназия | G26: Държавно | H26: 117 | I26: 118 | J26: 136 | K26: =+(H26+I26+J26)/3 -> 123.66667 | L26: 150000 | M26: =+L26*0.45 -> 67500 | N26: =+L26*0.45 -> 67500 | O26: =+N26*0.2 -> 13500 | P26: =++L26*0.1 -> 15000 | Q26: 30000 | R26: 3 | S26: =+Q26*0.1 -> 3000 | T26: =+L26+Q26 -> 180000 | U26: =+T26*0.01 -> 1800 | V26: =+T26+U26 -> 181800 | W26: 000017163
A27: 102009 | B27: Благоевград | C27: Петрич | D27: Петрич | E27: Професионална гимназия по механоелектротехника "Юрий Гагарин" | F27: професионална гимназия | G27: Държавно | H27: 273 | I27: 283 | J27: 270 | K27: =+(H27+I27+J27)/3 -> 275.33333 | L27: 200000 | M27: =+L27*0.45 -> 90000 | N27: =+L27*0.45 -> 90000 | O27: =+N27*0.2 -> 18000 | P27: =++L27*0.1 -> 20000 | Q27: 50000 | R27: 5 | S27: =+Q27*0.1 -> 5000 | T27: =+L27+Q27 -> 250000 | U27: =+T27*0.01 -> 2500 | V27: =+T27+U27 -> 252500 | W27: 000014231
A28: 102010 | B28: Благоевград | C28: Банско | D28: Банско | E28: Гимназия по туризъм "Алеко Константинов" | F28: професионална гимназия | G28: Общинско | H28: 79 | I28: 99 | J28: 98 | K28: =+(H28+I28+J28)/3 -> 92 | L28: 150000 | M28: =+L28*0.45 -> 67500 | N28: =+L28*0.45 -> 67500 | O28: =+N28*0.2 -> 13500 | P28: =++L28*0.1 -> 15000 | Q28: 30000 | R28: 3 | S28: =+Q28*0.1 -> 3000 | T28: =+L28+Q28 -> 180000 | U28: =+T28*0.01 -> 1800 | V28: =+T28+U28 -> 181800 | W28: 000014306
A29: 102011 | B29: Благоевград | C29: Якоруда | D29: Якоруда | E29: Професионална гимназия "Петко Рачов Славейков" | F29: професионална гимназия | G29: Държавно | H29: 165 | I29: 171 | J29: 180 | K29: =+(H29+I29+J29)/3 -> 172 | L29: 150000 | M29: =+L29*0.45 -> 67500 | N29: =+L29*0.45 -> 67500 | O29: =+N29*0.2 -> 13500 | P29: =++L29*0.1 -> 15000 | Q29: 30000 | R29: 3 | S29: =+Q29*0.1 -> 3000 | T29: =+L29+Q29 -> 180000 | U29: =+T29*0.01 -> 1800 | V29: =+T29+U29 -> 181800 | W29: 000014150
A30: 102012 | B30: Благоевград | C30: Разлог | D30: Разлог | E30: Разложка професионална гимназия "Никола Стойчев" | F30: професионална гимназия | G30: Държавно | H30: 224 | I30: 202 | J30: 203 | K30: =+(H30+I30+J30)/3 -> 209.66667 | L30: 200000 | M30: =+L30*0.45 -> 90000 | N30: =+L30*0.45 -> 90000 | O30: =+N30*0.2 -> 18000 | P30: =++L30*0.1 -> 20000 | Q30: 50000 | R30: 5 | S30: =+Q30*0.1 -> 5000 | T30: =+L30+Q30 -> 250000 | U30: =+T30*0.01 -> 2500 | V30: =+T30+U30 -> 252500 | W30: 000014199
A31: 102013 | B31: Благоевград | C31: Сандански | D31: Сандански | E31: Земеделска професионална гимназия "Климент Аркадиевич Тимирязев" | F31: професионална гимназия | G31: Общинско | H31: 731 | I31: 750 | J31: 760 | K31: =+(H31+I31+J31)/3 -> 747 | L31: =300000*0.7 -> 210000 | M31: =+L31*0.45 -> 94500 | N31: =+L31*0.45 -> 94500 | O31: =+N31*0.2 -> 18900 | P31: =++L31*0.1 -> 21000 | Q31: 60000 | R31: 6 | S31: =+Q31*0.1 -> 6000 | T31: =+L31+Q31 -> 270000 | U31: =+T31*0.01 -> 2700 | V31: =+T31+U31 -> 272700 | W31: 000014128
A32: 102014 | B32: Благоевград | C32: Петрич | D32: Петрич | E32: Професионална гимназия по икономика и туризъм " Проф. д-р Асен Златаров" | F32: професионална гимназия | G32: Държавно | H32: 527 | I32: 530 | J32: 504 | K32: =+(H32+I32+J32)/3 -> 520.33333 | L32: =300000 -> 300000 | M32: =+L32*0.45 -> 135000 | N32: =+L32*0.45 -> 135000 | O32: =+N32*0.2 -> 27000 | P32: =++L32*0.1 -> 30000 | Q32: 60000 | R32: 6 | S32: =+Q32*0.1 -> 6000 | T32: =+L32+Q32 -> 360000 | U32: =+T32*0.01 -> 3600 | V32: =+T32+U32 -> 363600 | W32: 101043817
A33: 102015 | B33: Благоевград | C33: Банско | D33: Банско | E33: Професионална гимназия по електроника и енергетика | F33: професионална гимназия | G33: Държавно | H33: 217 | I33: 223 | J33: 249 | K33: =+(H33+I33+J33)/3 -> 229.66667 | L33: 200000 | M33: =+L33*0.45 -> 90000 | N33: =+L33*0.45 -> 90000 | O33: =+N33*0.2 -> 18000 | P33: =++L33*0.1 -> 20000 | Q33: 50000 | R33: 5 | S33: =+Q33*0.1 -> 5000 | T33: =+L33+Q33 -> 250000 | U33: =+T33*0.01 -> 2500 | V33: =+T33+U33 -> 252500 | W33: 000014110
A34: 102016 | B34: Благоевград | C34: Гоце Делчев | D34: Гоце Делчев | E34: Професионална гимназия по механизация на селското стопанство "Пейо Крачолов Яворов" | F34: професионална гимназия | G34: Общинско | H34: 440 | I34: 442 | J34: 490 | K34: =+(H34+I34+J34)/3 -> 457.33333 | L34: =300000*0.7 -> 210000 | M34: =+L34*0.45 -> 94500 | N34: =+L34*0.45 -> 94500 | O34: =+N34*0.2 -> 18900 | P34: =++L34*0.1 -> 21000 | Q34: 60000 | R34: 6 | S34: =+Q34*0.1 -> 6000 | T34: =+L34+Q34 -> 270000 | U34: =+T34*0.01 -> 2700 | V34: =+T34+U34 -> 272700 | W34: 000014313
A35: 102017 | B35: Благоевград | C35: Разлог | D35: Разлог | E35: Професионална гимназия по механизация на селското стопанствo | F35: професионална гимназия | G35: Общинско | H35: 241 | I35: 258 | J35: 304 | K35: =+(H35+I35+J35)/3 -> 267.66667 | L35: 200000 | M35: =+L35*0.45 -> 90000 | N35: =+L35*0.45 -> 90000 | O35: =+N35*0.2 -> 18000 | P35: =++L35*0.1 -> 20000 | Q35: 50000 | R35: 5 | S35: =+Q35*0.1 -> 5000 | T35: =+L35+Q35 -> 250000 | U35: =+T35*0.01 -> 2500 | V35: =+T35+U35 -> 252500 | W35: 000014320
A36: 102060 | B36: Благоевград | C36: Благоевград | D36: Благоевград | E36: Пето средно училище "Георги Измирлиев" | F36: средно | G36: Общинско | H36: 436 | I36: 463 | J36: 490 | K36: =+(H36+I36+J36)/3 -> 463 | L36: =300000 -> 300000 | M36: =+L36*0.45 -> 135000 | N36: =+L36*0.45 -> 135000 | O36: =+N36*0.2 -> 27000 | P36: =++L36*0.1 -> 30000 | Q36: 60000 | R36: 6 | S36: =+Q36*0.1 -> 6000 | T36: =+L36+Q36 -> 360000 | U36: =+T36*0.01 -> 3600 | V36: =+T36+U36 -> 363600 | W36: 000012497
A37: 102113 | B37: Благоевград | C37: Разлог | D37: Разлог | E37: Професионална гимназия по транспорт | F37: професионална гимназия | G37: Държавно | H37: 303 | I37: 314 | J37: 307 | K37: =+(H37+I37+J37)/3 -> 308 | L37: 200000 | M37: =+L37*0.45 -> 90000 | N37: =+L37*0.45 -> 90000 | O37: =+N37*0.2 -> 18000 | P37: =++L37*0.1 -> 20000 | Q37: 50000 | R37: 5 | S37: =+Q37*0.1 -> 5000 | T37: =+L37+Q37 -> 250000 | U37: =+T37*0.01 -> 2500 | V37: =+T37+U37 -> 252500 | W37: 000016855
A38: 102606 | B38: Благоевград | C38: Сандански | D38: Сандански | E38: Второ основно училище "Христо Смирненски" | F38: основно | G38: Общинско | H38: 575 | I38: 596 | J38: 625 | K38: =+(H38+I38+J38)/3 -> 598.66667 | L38: =300000 -> 300000 | M38: =+L38*0.45 -> 135000 | N38: =+L38*0.45 -> 135000 | O38: =+N38*0.2 -> 27000 | P38: =++L38*0.1 -> 30000 | Q38: 60000 | R38: 6 | S38: =+Q38*0.1 -> 6000 | T38: =+L38+Q38 -> 360000 | U38: =+T38*0.01 -> 3600 | V38: =+T38+U38 -> 363600 | W38: 000012604
A39: 103002 | B39: Благоевград | C39: Гърмен | D39: Рибново | E39: Средно училище "Йордан Йовков" | F39: средно | G39: Общинско | H39: 552 | I39: 550 | J39: 574 | K39: =+(H39+I39+J39)/3 -> 558.66667 | L39: =300000 -> 300000 | M39: =+L39*0.45 -> 135000 | N39: =+L39*0.45 -> 135000 | O39: =+N39*0.2 -> 27000 | P39: =++L39*0.1 -> 30000 | Q39: 60000 | R39: 6 | S39: =+Q39*0.1 -> 6000 | T39: =+L39+Q39 -> 360000 | U39: =+T39*0.01 -> 3600 | V39: =+T39+U39 -> 363600 | W39: 000013115
A40: 103004 | B40: Благоевград | C40: Гърмен | D40: Огняново | E40: Основно училище "Пейо Крачолов Яворов" | F40: основно | G40: Общинско | H40: 127 | I40: 135 | J40: 126 | K40: =+(H40+I40+J40)/3 -> 129.33333 | L40: 150000 | M40: =+L40*0.45 -> 67500 | N40: =+L40*0.45 -> 67500 | O40: =+N40*0.2 -> 13500 | P40: =++L40*0.1 -> 15000 | Q40: 30000 | R40: 3 | S40: =+Q40*0.1 -> 3000 | T40: =+L40+Q40 -> 180000 | U40: =+T40*0.01 -> 1800 | V40: =+T40+U40 -> 181800 | W40: 000013097
A41: 103005 | B41: Благоевград | C41: Гърмен | D41: Дебрен | E41: Обединено училище "Св. Климент Охридски" | F41: обединено | G41: Общинско | H41: 215 | I41: 219 | J41: 219 | K41: =+(H41+I41+J41)/3 -> 217.66667 | L41: 200000 | M41: =+L41*0.45 -> 90000 | N41: =+L41*0.45 -> 90000 | O41: =+N41*0.2 -> 18000 | P41: =++L41*0.1 -> 20000 | Q41: 50000 | R41: 5 | S41: =+Q41*0.1 -> 5000 | T41: =+L41+Q41 -> 250000 | U41: =+T41*0.01 -> 2500 | V41: =+T41+U41 -> 252500 | W41: 000012967
A42: 103006 | B42: Благоевград | C42: Гърмен | D42: Горно Дряново | E42: Основно училище " Св. Паисий Хилендарски" | F42: основно | G42: Общинско | H42: 100 | I42: 91 | J42: 83 | K42: =+(H42+I42+J42)/3 -> 91.333333 | L42: 150000 | M42: =+L42*0.45 -> 67500 | N42: =+L42*0.45 -> 67500 | O42: =+N42*0.2 -> 13500 | P42: =++L42*0.1 -> 15000 | Q42: 30000 | R42: 3 | S42: =+Q42*0.1 -> 3000 | T42: =+L42+Q42 -> 180000 | U42: =+T42*0.01 -> 1800 | V42: =+T42+U42 -> 181800 | W42: 000012950
A43: 103008 | B43: Благоевград | C43: Гърмен | D43: Долно Дряново | E43: Обединено училище "Христо Ботев" | F43: обединено | G43: Общинско | H43: 179 | I43: 179 | J43: 174 | K43: =+(H43+I43+J43)/3 -> 177.33333 | L43: =150000*0.7 -> 105000 | M43: =+L43*0.45 -> 47250 | N43: =+L43*0.45 -> 47250 | O43: =+N43*0.2 -> 9450 | P43: =++L43*0.1 -> 10500 | Q43: 30000 | R43: 3 | S43: =+Q43*0.1 -> 3000 | T43: =+L43+Q43 -> 135000 | U43: =+T43*0.01 -> 1350 | V43: =+T43+U43 -> 136350 | W43: 000011477
A44: 103009 | B44: Благоевград | C44: Гърмен | D44: Хвостяне | E44: Основно училище"Димитър Талев" | F44: основно | G44: Общинско | H44: 60 | I44: 60 | J44: 62 | K44: =+(H44+I44+J44)/3 -> 60.666667 | L44: 150000 | M44: =+L44*0.45 -> 67500 | N44: =+L44*0.45 -> 67500 | O44: =+N44*0.2 -> 13500 | P44: =++L44*0.1 -> 15000 | Q44: 30000 | R44: 3 | S44: =+Q44*0.1 -> 3000 | T44: =+L44+Q44 -> 180000 | U44: =+T44*0.01 -> 1800 | V44: =+T44+U44 -> 181800 | W44: 000011502
A45: 103019 | B45: Благоевград | C45: Гърмен | D45: Дъбница | E45: Обединено училище "Христо Ботев" | F45: обединено | G45: Общинско | H45: 150 | I45: 153 | J45: 160 | K45: =+(H45+I45+J45)/3 -> 154.33333 | L45: =150000*0.7 -> 105000 | M45: =+L45*0.45 -> 47250 | N45: =+L45*0.45 -> 47250 | O45: =+N45*0.2 -> 9450 | P45: =++L45*0.1 -> 10500 | Q45: 30000 | R45: 3 | S45: =+Q45*0.1 -> 3000 | T45: =+L45+Q45 -> 135000 | U45: =+T45*0.01 -> 1350 | V45: =+T45+U45 -> 136350 | W45: 000013019
A46: 103133 | B46: Благоевград | C46: Симитли | D46: Симитли | E46: Средно училище "Св. Св. Кирил и Методий" | F46: средно | G46: Общинско | H46: 650 | I46: 626 | J46: 614 | K46: =+(H46+I46+J46)/3 -> 630 | L46: =300000 -> 300000 | M46: =+L46*0.45 -> 135000 | N46: =+L46*0.45 -> 135000 | O46: =+N46*0.2 -> 27000 | P46: =++L46*0.1 -> 30000 | Q46: 60000 | R46: 6 | S46: =+Q46*0.1 -> 6000 | T46: =+L46+Q46 -> 360000 | U46: =+T46*0.01 -> 3600 | V46: =+T46+U46 -> 363600 | W46: 000013962
A47: 103310 | B47: Благоевград | C47: Петрич | D47: Петрич | E47: Средно училище "Никола Йонков Вапцаров" | F47: средно | G47: Общинско | H47: 914 | I47: 909 | J47: 900 | K47: =+(H47+I47+J47)/3 -> 907.66667 | L47: =300000 -> 300000 | M47: =+L47*0.45 -> 135000 | N47: =+L47*0.45 -> 135000 | O47: =+N47*0.2 -> 27000 | P47: =++L47*0.1 -> 30000 | Q47: 60000 | R47: 6 | S47: =+Q47*0.1 -> 6000 | T47: =+L47+Q47 -> 360000 | U47: =+T47*0.01 -> 3600 | V47: =+T47+U47 -> 363600 | W47: 000012586
A48: 103401 | B48: Благоевград | C48: Гоце Делчев | D48: Брезница | E48: Средно училище "Св. Св. Кирил и Методий" | F48: средно | G48: Общинско | H48: 398 | I48: 410 | J48: 401 | K48: =+(H48+I48+J48)/3 -> 403 | L48: =300000 -> 300000 | M48: =+L48*0.45 -> 135000 | N48: =+L48*0.45 -> 135000 | O48: =+N48*0.2 -> 27000 | P48: =++L48*0.1 -> 30000 | Q48: 60000 | R48: 6 | S48: =+Q48*0.1 -> 6000 | T48: =+L48+Q48 -> 360000 | U48: =+T48*0.01 -> 3600 | V48: =+T48+U48 -> 363600 | W48: 000012878
A49: 103402 | B49: Благоевград | C49: Гоце Делчев | D49: Гоце Делчев | E49: Първо основно училище "Св. Св. Кирил и Методий" | F49: основно | G49: Общинско | H49: 580 | I49: 585 | J49: 565 | K49: =+(H49+I49+J49)/3 -> 576.66667 | L49: =300000 -> 300000 | M49: =+L49*0.45 -> 135000 | N49: =+L49*0.45 -> 135000 | O49: =+N49*0.2 -> 27000 | P49: =++L49*0.1 -> 30000 | Q49: 60000 | R49: 6 | S49: =+Q49*0.1 -> 6000 | T49: =+L49+Q49 -> 360000 | U49: =+T49*0.01 -> 3600 | V49: =+T49+U49 -> 363600 | W49: 000012522
A50: 103403 | B50: Благоевград | C50: Гоце Делчев | D50: Гоце Делчев | E50: Второ основно училище "Гоце Делчев" | F50: основно | G50: Общинско | H50: 535 | I50: 531 | J50: 531 | K50: =+(H50+I50+J50)/3 -> 532.33333 | L50: =300000 -> 300000 | M50: =+L50*0.45 -> 135000 | N50: =+L50*0.45 -> 135000 | O50: =+N50*0.2 -> 27000 | P50: =++L50*0.1 -> 30000 | Q50: 60000 | R50: 6 | S50: =+Q50*0.1 -> 6000 | T50: =+L50+Q50 -> 360000 | U50: =+T50*0.01 -> 3600 | V50: =+T50+U50 -> 363600 | W50: 000012530
A51: 103404 | B51: Благоевград | C51: Гоце Делчев | D51: Гоце Делчев | E51: Трето основно училище "Братя Миладинови" | F51: основно | G51: Общинско | H51: 310 | I51: 294 | J51: 312 | K51: =+(H51+I51+J51)/3 -> 305.33333 | L51: 200000 | M51: =+L51*0.45 -> 90000 | N51: =+L51*0.45 -> 90000 | O51: =+N51*0.2 -> 18000 | P51: =++L51*0.1 -> 20000 | Q51: 50000 | R51: 5 | S51: =+Q51*0.1 -> 5000 | T51: =+L51+Q51 -> 250000 | U51: =+T51*0.01 -> 2500 | V51: =+T51+U51 -> 252500 | W51: 000010902
A52: 103405 | B52: Благоевград | C52: Гоце Делчев | D52: Мосомище | E52: Основно училище "Христо Ботев" | F52: основно | G52: Общинско | H52: 103 | I52: 99 | J52: 85 | K52: =+(H52+I52+J52)/3 -> 95.666667 | L52: 150000 | M52: =+L52*0.45 -> 67500 | N52: =+L52*0.45 -> 67500 | O52: =+N52*0.2 -> 13500 | P52: =++L52*0.1 -> 15000 | Q52: 30000 | R52: 3 | S52: =+Q52*0.1 -> 3000 | T52: =+L52+Q52 -> 180000 | U52: =+T52*0.01 -> 1800 | V52: =+T52+U52 -> 181800 | W52: 000012935
A53: 103406 | B53: Благоевград | C53: Гоце Делчев | D53: Борово | E53: Основно училище "Св. Климент Охридски" | F53: основно | G53: Общинско | H53: 65 | I53: 67 | J53: 69 | K53: =+(H53+I53+J53)/3 -> 67 | L53: 150000 | M53: =+L53*0.45 -> 67500 | N53: =+L53*0.45 -> 67500 | O53: =+N53*0.2 -> 13500 | P53: =++L53*0.1 -> 15000 | Q53: 30000 | R53: 3 | S53: =+Q53*0.1 -> 3000 | T53: =+L53+Q53 -> 180000 | U53: =+T53*0.01 -> 1800 | V53: =+T53+U53 -> 181800 | W53: 000011413
A54: 103407 | B54: Благоевград | C54: Гоце Делчев | D54: Буково | E54: Основно училище " Иван Вазов" | F54: основно | G54: Общинско | H54: 83 | I54: 79 | J54: 69 | K54: =+(H54+I54+J54)/3 -> 77 | L54: 150000 | M54: =+L54*0.45 -> 67500 | N54: =+L54*0.45 -> 67500 | O54: =+N54*0.2 -> 13500 | P54: =++L54*0.1 -> 15000 | Q54: 30000 | R54: 3 | S54: =+Q54*0.1 -> 3000 | T54: =+L54+Q54 -> 180000 | U54: =+T54*0.01 -> 1800 | V54: =+T54+U54 -> 181800 | W54: 000012885
A55: 103408 | B55: Благоевград | C55: Гоце Делчев | D55: Баничан | E55: Основно училище "Свети Паисий Хилендарски" | F55: основно | G55: Общинско | H55: 43 | I55: 36 | J55: 33 | K55: =+(H55+I55+J55)/3 -> 37.333333 | L55: 50000 | M55: =+L55*0.45 -> 22500 | N55: =+L55*0.45 -> 22500 | O55: =+N55*0.2 -> 4500 | P55: =++L55*0.1 -> 5000 | Q55: 10000 | R55: 1 | S55: =+Q55*0.1 -> 1000 | T55: =+L55+Q55 -> 60000 | U55: =+T55*0.01 -> 600 | V55: =+T55+U55 -> 60600 | W55: 000012860
A56: 103409 | B56: Благоевград | C56: Гоце Делчев | D56: Лъжница | E56: Обединено училище "Петър Берон" | F56: обединено | G56: Общинско | H56: 158 | I56: 133 | J56: 135 | K56: =+(H56+I56+J56)/3 -> 142 | L56: 150000 | M56: =+L56*0.45 -> 67500 | N56: =+L56*0.45 -> 67500 | O56: =+N56*0.2 -> 13500 | P56: =++L56*0.1 -> 15000 | Q56: 30000 | R56: 3 | S56: =+Q56*0.1 -> 3000 | T56: =+L56+Q56 -> 180000 | U56: =+T56*0.01 -> 1800 | V56: =+T56+U56 -> 181800 | W56: 000012928
A57: 103410 | B57: Благоевград | C57: Гоце Делчев | D57: Корница | E57: Oбединено училище "Св. Паисий Хилендарски" | F57: обединено | G57: Общинско | H57: 120 | I57: 108 | J57: 106 | K57: =+(H57+I57+J57)/3 -> 111.33333 | L57: 150000 | M57: =+L57*0.45 -> 67500 | N57: =+L57*0.45 -> 67500 | O57: =+N57*0.2 -> 13500 | P57: =++L57*0.1 -> 15000 | Q57: 30000 | R57: 3 | S57: =+Q57*0.1 -> 3000 | T57: =+L57+Q57 -> 180000 | U57: =+T57*0.01 -> 1800 | V57: =+T57+U57 -> 181800 | W57: 000012910
A58: 103411 | B58: Благоевград | C58: Гоце Делчев | D58: Гоце Делчев | E58: Център за специална образователна подкрепа "Васил Левски" | F58: център за специална образователна подкрепа | G58: Държавно | H58: 85 | I58: 80 | J58: 81 | K58: =+(H58+I58+J58)/3 -> 82 | L58: 150000 | M58: =+L58*0.45 -> 67500 | N58: =+L58*0.45 -> 67500 | O58: =+N58*0.2 -> 13500 | P58: =++L58*0.1 -> 15000 | Q58: 30000 | R58: 3 | S58: =+Q58*0.1 -> 3000 | T58: =+L58+Q58 -> 180000 | U58: =+T58*0.01 -> 1800 | V58: =+T58+U58 -> 181800 | W58: 000016990
A59: 103501 | B59: Благоевград | C59: Разлог | D59: Разлог | E59: Средно училище "Братя Петър и Иван Каназиреви" | F59: средно | G59: Общинско | H59: 576 | I59: 592 | J59: 595 | K59: =+(H59+I59+J59)/3 -> 587.66667 | L59: =300000 -> 300000 | M59: =+L59*0.45 -> 135000 | N59: =+L59*0.45 -> 135000 | O59: =+N59*0.2 -> 27000 | P59: =++L59*0.1 -> 30000 | Q59: 60000 | R59: 6 | S59: =+Q59*0.1 -> 6000 | T59: =+L59+Q59 -> 360000 | U59: =+T59*0.01 -> 3600 | V59: =+T59+U59 -> 363600 | W59: 000013948
A60: 103502 | B60: Благоевград | C60: Разлог | D60: Разлог | E60: Основно училище "Никола Парапунов" | F60: основно | G60: Общинско | H60: 396 | I60: 401 | J60: 396 | K60: =+(H60+I60+J60)/3 -> 397.66667 | L60: 200000 | M60: =+L60*0.45 -> 90000 | N60: =+L60*0.45 -> 90000 | O60: =+N60*0.2 -> 18000 | P60: =++L60*0.1 -> 20000 | Q60: 50000 | R60: 5 | S60: =+Q60*0.1 -> 5000 | T60: =+L60+Q60 -> 250000 | U60: =+T60*0.01 -> 2500 | V60: =+T60+U60 -> 252500 | W60: 000013909
A61: 103503 | B61: Благоевград | C61: Разлог | D61: Баня | E61: Основно училище "Св. Паисий Хилендарски" | F61: основно | G61: Общинско | H61: 228 | I61: 214 | J61: 204 | K61: =+(H61+I61+J61)/3 -> 215.33333 | L61: 200000 | M61: =+L61*0.45 -> 90000 | N61: =+L61*0.45 -> 90000 | O61: =+N61*0.2 -> 18000 | P61: =++L61*0.1 -> 20000 | Q61: 50000 | R61: 5 | S61: =+Q61*0.1 -> 5000 | T61: =+L61+Q61 -> 250000 | U61: =+T61*0.01 -> 2500 | V61: =+T61+U61 -> 252500 | W61: 000012636
A62: 103504 | B62: Благоевград | C62: Разлог | D62: Бачево | E62: Основно училище "Св. Св. Кирил и Методий" | F62: основно | G62: Общинско | H62: 93 | I62: 98 | J62: 105 | K62: =+(H62+I62+J62)/3 -> 98.666667 | L62: 150000 | M62: =+L62*0.45 -> 67500 | N62: =+L62*0.45 -> 67500 | O62: =+N62*0.2 -> 13500 | P62: =++L62*0.1 -> 15000 | Q62: 30000 | R62: 3 | S62: =+Q62*0.1 -> 3000 | T62: =+L62+Q62 -> 180000 | U62: =+T62*0.01 -> 1800 | V62: =+T62+U62 -> 181800 | W62: 000013236
A63: 103506 | B63: Благоевград | C63: Разлог | D63: Горно Драглище | E63: Основно училище "Неофит Рилски" | F63: основно | G63: Общинско | H63: 62 | I63: 62 | J63: 70 | K63: =+(H63+I63+J63)/3 -> 64.666667 | L63: 150000 | M63: =+L63*0.45 -> 67500 | N63: =+L63*0.45 -> 67500 | O63: =+N63*0.2 -> 13500 | P63: =++L63*0.1 -> 15000 | Q63: 30000 | R63: 3 | S63: =+Q63*0.1 -> 3000 | T63: =+L63+Q63 -> 180000 | U63: =+T63*0.01 -> 1800 | V63: =+T63+U63 -> 181800 | W63: 000012692
A64: 103508 | B64: Благоевград | C64: Разлог | D64: Елешница | E64: Основно училище"Братя Миладинови" | F64: основно | G64: Общинско | H64: 84 | I64: 83 | J64: 81 | K64: =+(H64+I64+J64)/3 -> 82.666667 | L64: 150000 | M64: =+L64*0.45 -> 67500 | N64: =+L64*0.45 -> 67500 | O64: =+N64*0.2 -> 13500 | P64: =++L64*0.1 -> 15000 | Q64: 30000 | R64: 3 | S64: =+Q64*0.1 -> 3000 | T64: =+L64+Q64 -> 180000 | U64: =+T64*0.01 -> 1800 | V64: =+T64+U64 -> 181800 | W64: 000013026
A65: 103509 | B65: Благоевград | C65: Разлог | D65: Долно Драглище | E65: Център за специална образователна подкрепа "Рилска иглика" | F65: център за специална образователна подкрепа | G65: Държавно | H65: 50 | I65: 46 | J65: 40 | K65: =+(H65+I65+J65)/3 -> 45.333333 | L65: 50000 | M65: =+L65*0.45 -> 22500 | N65: =+L65*0.45 -> 22500 | O65: =+N65*0.2 -> 4500 | P65: =++L65*0.1 -> 5000 | Q65: 10000 | R65: 1 | S65: =+Q65*0.1 -> 1000 | T65: =+L65+Q65 -> 60000 | U65: =+T65*0.01 -> 600 | V65: =+T65+U65 -> 60600 | W65: 000014039
A66: 103510 | B66: Благоевград | C66: Разлог | D66: Разлог | E66: Начално училище "Яне Сандански" | F66: начално | G66: Общинско | H66: 117 | I66: 118 | J66: 109 | K66: =+(H66+I66+J66)/3 -> 114.66667 | L66: 150000 | M66: =+L66*0.45 -> 67500 | N66: =+L66*0.45 -> 67500 | O66: =+N66*0.2 -> 13500 | P66: =++L66*0.1 -> 15000 | Q66: 30000 | R66: 3 | S66: =+Q66*0.1 -> 3000 | T66: =+L66+Q66 -> 180000 | U66: =+T66*0.01 -> 1800 | V66: =+T66+U66 -> 181800 | W66: 000010927
A67: 103511 | B67: Благоевград | C67: Разлог | D67: Разлог | E67: Начално училище"Св.Св.Кирил и Методий" | F67: начално | G67: Общинско | H67: 147 | I67: 142 | J67: 126 | K67: =+(H67+I67+J67)/3 -> 138.33333 | L67: 150000 | M67: =+L67*0.45 -> 67500 | N67: =+L67*0.45 -> 67500 | O67: =+N67*0.2 -> 13500 | P67: =++L67*0.1 -> 15000 | Q67: 30000 | R67: 3 | S67: =+Q67*0.1 -> 3000 | T67: =+L67+Q67 -> 180000 | U67: =+T67*0.01 -> 1800 | V67: =+T67+U67 -> 181800 | W67: 000010934
A68: 104001 | B68: Благоевград | C68: Петрич | D68: Петрич | E68: Профилирана гимназия "Пейо Крачолов Яворов" | F68: профилирана гимназия | G68: Общинско | H68: 630 | I68: 639 | J68: 656 | K68: =+(H68+I68+J68)/3 -> 641.66667 | L68: =300000 -> 300000 | M68: =+L68*0.45 -> 135000 | N68: =+L68*0.45 -> 135000 | O68: =+N68*0.2 -> 27000 | P68: =++L68*0.1 -> 30000 | Q68: 60000 | R68: 6 | S68: =+Q68*0.1 -> 6000 | T68: =+L68+Q68 -> 360000 | U68: =+T68*0.01 -> 3600 | V68: =+T68+U68 -> 363600 | W68: 000013930
A69: 104002 | B69: Благоевград | C69: Петрич | D69: Петрич | E69: Средно училище "Антон Попов" | F69: средно | G69: Общинско | H69: 332 | I69: 343 | J69: 373 | K69: =+(H69+I69+J69)/3 -> 349.33333 | L69: 200000 | M69: =+L69*0.45 -> 90000 | N69: =+L69*0.45 -> 90000 | O69: =+N69*0.2 -> 18000 | P69: =++L69*0.1 -> 20000 | Q69: 50000 | R69: 5 | S69: =+Q69*0.1 -> 5000 | T69: =+L69+Q69 -> 250000 | U69: =+T69*0.01 -> 2500 | V69: =+T69+U69 -> 252500 | W69: 000019417
A70: 104003 | B70: Благоевград | C70: Петрич | D70: Коларово | E70: Средно училище "Васил Левски" | F70: средно | G70: Общинско | H70: 204 | I70: 212 | J70: 211 | K70: =+(H70+I70+J70)/3 -> 209 | L70: 200000 | M70: =+L70*0.45 -> 90000 | N70: =+L70*0.45 -> 90000 | O70: =+N70*0.2 -> 18000 | P70: =++L70*0.1 -> 20000 | Q70: 50000 | R70: 5 | S70: =+Q70*0.1 -> 5000 | T70: =+L70+Q70 -> 250000 | U70: =+T70*0.01 -> 2500 | V70: =+T70+U70 -> 252500 | W70: 000013439
A71: 104004 | B71: Благоевград | C71: Петрич | D71: Първомай | E71: Средно училище "Св.Паисий Хилендарски" | F71: средно | G71: Общинско | H71: 392 | I71: 377 | J71: 367 | K71: =+(H71+I71+J71)/3 -> 378.66667 | L71: 200000 | M71: =+L71*0.45 -> 90000 | N71: =+L71*0.45 -> 90000 | O71: =+N71*0.2 -> 18000 | P71: =++L71*0.1 -> 20000 | Q71: 50000 | R71: 5 | S71: =+Q71*0.1 -> 5000 | T71: =+L71+Q71 -> 250000 | U71: =+T71*0.01 -> 2500 | V71: =+T71+U71 -> 252500 | W71: 000013211
A72: 104005 | B72: Благоевград | C72: Петрич | D72: Скрът | E72: Основно училище "Пейо Крачолов Яворов" | F72: основно | G72: Общинско | H72: 114 | I72: 102 | J72: 103 | K72: =+(H72+I72+J72)/3 -> 106.33333 | L72: 150000 | M72: =+L72*0.45 -> 67500 | N72: =+L72*0.45 -> 67500 | O72: =+N72*0.2 -> 13500 | P72: =++L72*0.1 -> 15000 | Q72: 30000 | R72: 3 | S72: =+Q72*0.1 -> 3000 | T72: =+L72+Q72 -> 180000 | U72: =+T72*0.01 -> 1800 | V72: =+T72+U72 -> 181800 | W72: 000013460
A73: 104006 | B73: Благоевград | C73: Петрич | D73: Петрич | E73: Първо основно училище "Кочо Мавродиев" | F73: основно | G73: Общинско | H73: 303 | I73: 295 | J73: 295 | K73: =+(H73+I73+J73)/3 -> 297.66667 | L73: 200000 | M73: =+L73*0.45 -> 90000 | N73: =+L73*0.45 -> 90000 | O73: =+N73*0.2 -> 18000 | P73: =++L73*0.1 -> 20000 | Q73: 50000 | R73: 5 | S73: =+Q73*0.1 -> 5000 | T73: =+L73+Q73 -> 250000 | U73: =+T73*0.01 -> 2500 | V73: =+T73+U73 -> 252500 | W73: 000012561
A74: 104007 | B74: Благоевград | C74: Петрич | D74: Петрич | E74: Трето основно училище "Гоце Делчев" | F74: основно | G74: Общинско | H74: 480 | I74: 466 | J74: 434 | K74: =+(H74+I74+J74)/3 -> 460 | L74: =300000 -> 300000 | M74: =+L74*0.45 -> 135000 | N74: =+L74*0.45 -> 135000 | O74: =+N74*0.2 -> 27000 | P74: =++L74*0.1 -> 30000 | Q74: 60000 | R74: 6 | S74: =+Q74*0.1 -> 6000 | T74: =+L74+Q74 -> 360000 | U74: =+T74*0.01 -> 3600 | V74: =+T74+U74 -> 363600 | W74: 000012579
A75: 104008 | B75: Благоевград | C75: Петрич | D75: Петрич | E75: Четвърто основно училище"Христо Смирненски" | F75: основно | G75: Общинско | H75: 525 | I75: 541 | J75: 567 | K75: =+(H75+I75+J75)/3 -> 544.33333 | L75: =300000 -> 300000 | M75: =+L75*0.45 -> 135000 | N75: =+L75*0.45 -> 135000 | O75: =+N75*0.2 -> 27000 | P75: =++L75*0.1 -> 30000 | Q75: 60000 | R75: 6 | S75: =+Q75*0.1 -> 6000 | T75: =+L75+Q75 -> 360000 | U75: =+T75*0.01 -> 3600 | V75: =+T75+U75 -> 363600 | W75: 000012554
A76: 104017 | B76: Благоевград | C76: Петрич | D76: Рупите | E76: Основно училище "Св.Св. Кирил и Методий" | F76: основно | G76: Общинско | H76: 100 | I76: 103 | J76: 93 | K76: =+(H76+I76+J76)/3 -> 98.666667 | L76: 150000 | M76: =+L76*0.45 -> 67500 | N76: =+L76*0.45 -> 67500 | O76: =+N76*0.2 -> 13500 | P76: =++L76*0.1 -> 15000 | Q76: 30000 | R76: 3 | S76: =+Q76*0.1 -> 3000 | T76: =+L76+Q76 -> 180000 | U76: =+T76*0.01 -> 1800 | V76: =+T76+U76 -> 181800 | W76: 000013631
A77: 104018 | B77: Благоевград | C77: Петрич | D77: Марикостиново | E77: Основно училище "Св. Св. Кирил и Методий" | F77: основно | G77: Общинско | H77: 98 | I77: 99 | J77: 95 | K77: =+(H77+I77+J77)/3 -> 97.333333 | L77: 150000 | M77: =+L77*0.45 -> 67500 | N77: =+L77*0.45 -> 67500 | O77: =+N77*0.2 -> 13500 | P77: =++L77*0.1 -> 15000 | Q77: 30000 | R77: 3 | S77: =+Q77*0.1 -> 3000 | T77: =+L77+Q77 -> 180000 | U77: =+T77*0.01 -> 1800 | V77: =+T77+U77 -> 181800 | W77: 000013670
A78: 104024 | B78: Благоевград | C78: Петрич | D78: Кавракирово | E78: Основно училище "Св. Св. Кирил и Методий" | F78: основно | G78: Общинско | H78: 147 | I78: 134 | J78: 130 | K78: =+(H78+I78+J78)/3 -> 137 | L78: 150000 | M78: =+L78*0.45 -> 67500 | N78: =+L78*0.45 -> 67500 | O78: =+N78*0.2 -> 13500 | P78: =++L78*0.1 -> 15000 | Q78: 30000 | R78: 3 | S78: =+Q78*0.1 -> 3000 | T78: =+L78+Q78 -> 180000 | U78: =+T78*0.01 -> 1800 | V78: =+T78+U78 -> 181800 | W78: 000013204
A79: 104025 | B79: Благоевград | C79: Петрич | D79: Кърналово | E79: Основно училище "Братя Миладинови" | F79: основно | G79: Общинско | H79: 106 | I79: 97 | J79: 90 | K79: =+(H79+I79+J79)/3 -> 97.666667 | L79: 150000 | M79: =+L79*0.45 -> 67500 | N79: =+L79*0.45 -> 67500 | O79: =+N79*0.2 -> 13500 | P79: =++L79*0.1 -> 15000 | Q79: 30000 | R79: 3 | S79: =+Q79*0.1 -> 3000 | T79: =+L79+Q79 -> 180000 | U79: =+T79*0.01 -> 1800 | V79: =+T79+U79 -> 181800 | W79: 811147785
A80: 104101 | B80: Благоевград | C80: Сандански | D80: Сандански | E80: Профилирана гимназия "Яне Сандански" | F80: профилирана гимназия | G80: Общинско | H80: 535 | I80: 547 | J80: 573 | K80: =+(H80+I80+J80)/3 -> 551.66667 | L80: =300000 -> 300000 | M80: =+L80*0.45 -> 135000 | N80: =+L80*0.45 -> 135000 | O80: =+N80*0.2 -> 27000 | P80: =++L80*0.1 -> 30000 | Q80: 60000 | R80: 6 | S80: =+Q80*0.1 -> 6000 | T80: =+L80+Q80 -> 360000 | U80: =+T80*0.01 -> 3600 | V80: =+T80+U80 -> 363600 | W80: 000013955
A81: 104104 | B81: Благоевград | C81: Сандански | D81: Сандански | E81: Първо основно училище "Свети Климент Охридски" | F81: основно | G81: Общинско | H81: 463 | I81: 457 | J81: 475 | K81: =+(H81+I81+J81)/3 -> 465 | L81: =300000 -> 300000 | M81: =+L81*0.45 -> 135000 | N81: =+L81*0.45 -> 135000 | O81: =+N81*0.2 -> 27000 | P81: =++L81*0.1 -> 30000 | Q81: 60000 | R81: 6 | S81: =+Q81*0.1 -> 6000 | T81: =+L81+Q81 -> 360000 | U81: =+T81*0.01 -> 3600 | V81: =+T81+U81 -> 363600 | W81: 000012593
A82: 104106 | B82: Благоевград | C82: Сандански | D82: Сандански | E82: Трето основно училище "Христо Ботев" | F82: основно | G82: Общинско | H82: 805 | I82: 798 | J82: 793 | K82: =+(H82+I82+J82)/3 -> 798.66667 | L82: =300000 -> 300000 | M82: =+L82*0.45 -> 135000 | N82: =+L82*0.45 -> 135000 | O82: =+N82*0.2 -> 27000 | P82: =++L82*0.1 -> 30000 | Q82: 60000 | R82: 6 | S82: =+Q82*0.1 -> 6000 | T82: =+L82+Q82 -> 360000 | U82: =+T82*0.01 -> 3600 | V82: =+T82+U82 -> 363600 | W82: 000010959
A83: 104107 | B83: Благоевград | C83: Сандански | D83: Сандански | E83: Четвърто основно училище " Св. Св. Козма и Дамян " | F83: основно | G83: Общинско | H83: 307 | I83: 314 | J83: 315 | K83: =+(H83+I83+J83)/3 -> 312 | L83: 200000 | M83: =+L83*0.45 -> 90000 | N83: =+L83*0.45 -> 90000 | O83: =+N83*0.2 -> 18000 | P83: =++L83*0.1 -> 20000 | Q83: 50000 | R83: 5 | S83: =+Q83*0.1 -> 5000 | T83: =+L83+Q83 -> 250000 | U83: =+T83*0.01 -> 2500 | V83: =+T83+U83 -> 252500 | W83: 000019488
A84: 104111 | B84: Благоевград | C84: Сандански | D84: Склаве | E84: Основно училище "Братя Миладинови" | F84: основно | G84: Общинско | H84: 121 | I84: 118 | J84: 120 | K84: =+(H84+I84+J84)/3 -> 119.66667 | L84: 150000 | M84: =+L84*0.45 -> 67500 | N84: =+L84*0.45 -> 67500 | O84: =+N84*0.2 -> 13500 | P84: =++L84*0.1 -> 15000 | Q84: 30000 | R84: 3 | S84: =+Q84*0.1 -> 3000 | T84: =+L84+Q84 -> 180000 | U84: =+T84*0.01 -> 1800 | V84: =+T84+U84 -> 181800 | W84: 000013745
A85: 104113 | B85: Благоевград | C85: Сандански | D85: Дамяница | E85: Основно училище "Св.Св. Кирил и Методий" | F85: основно | G85: Общинско | H85: 123 | I85: 120 | J85: 115 | K85: =+(H85+I85+J85)/3 -> 119.33333 | L85: 150000 | M85: =+L85*0.45 -> 67500 | N85: =+L85*0.45 -> 67500 | O85: =+N85*0.2 -> 13500 | P85: =++L85*0.1 -> 15000 | Q85: 30000 | R85: 3 | S85: =+Q85*0.1 -> 3000 | T85: =+L85+Q85 -> 180000 | U85: =+T85*0.01 -> 1800 | V85: =+T85+U85 -> 181800 | W85: 000013706
A86: 104116 | B86: Благоевград | C86: Сандански | D86: Катунци | E86: Основно училище"Христо Ботев" | F86: основно | G86: Общинско | H86: 35 | I86: 28 | J86: 28 | K86: =+(H86+I86+J86)/3 -> 30.333333 | L86: 50000 | M86: =+L86*0.45 -> 22500 | N86: =+L86*0.45 -> 22500 | O86: =+N86*0.2 -> 4500 | P86: =++L86*0.1 -> 5000 | Q86: 10000 | R86: 1 | S86: =+Q86*0.1 -> 1000 | T86: =+L86+Q86 -> 60000 | U86: =+T86*0.01 -> 600 | V86: =+T86+U86 -> 60600 | W86: 000013976
A87: 105001 | B87: Благоевград | C87: Белица | D87: Белица | E87: Средно училище "Св.Св.Кирил и Методий" | F87: средно | G87: Общинско | H87: 502 | I87: 490 | J87: 490 | K87: =+(H87+I87+J87)/3 -> 494 | L87: =300000 -> 300000 | M87: =+L87*0.45 -> 135000 | N87: =+L87*0.45 -> 135000 | O87: =+N87*0.2 -> 27000 | P87: =++L87*0.1 -> 30000 | Q87: 60000 | R87: 6 | S87: =+Q87*0.1 -> 6000 | T87: =+L87+Q87 -> 360000 | U87: =+T87*0.01 -> 3600 | V87: =+T87+U87 -> 363600 | W87: 000012515
A88: 105002 | B88: Благоевград | C88: Белица | D88: Белица | E88: Професионална гимназия "Никола Йонков Вапцаров" | F88: професионална гимназия | G88: Общинско | H88: 122 | I88: 138 | J88: 160 | K88: =+(H88+I88+J88)/3 -> 140 | L88: 150000 | M88: =+L88*0.45 -> 67500 | N88: =+L88*0.45 -> 67500 | O88: =+N88*0.2 -> 13500 | P88: =++L88*0.1 -> 15000 | Q88: 30000 | R88: 3 | S88: =+Q88*0.1 -> 3000 | T88: =+L88+Q88 -> 180000 | U88: =+T88*0.01 -> 1800 | V88: =+T88+U88 -> 181800 | W88: 000013987
A89: 105003 | B89: Благоевград | C89: Белица | D89: Краище | E89: Основно училище "Св.Паисий Хилендарски" | F89: основно | G89: Общинско | H89: 236 | I89: 230 | J89: 223 | K89: =+(H89+I89+J89)/3 -> 229.66667 | L89: 200000 | M89: =+L89*0.45 -> 90000 | N89: =+L89*0.45 -> 90000 | O89: =+N89*0.2 -> 18000 | P89: =++L89*0.1 -> 20000 | Q89: 50000 | R89: 5 | S89: =+Q89*0.1 -> 5000 | T89: =+L89+Q89 -> 250000 | U89: =+T89*0.01 -> 2500 | V89: =+T89+U89 -> 252500 | W89: 000012650
A90: 105004 | B90: Благоевград | C90: Белица | D90: Горно Краище | E90: Основно училище "Пейо Крачолов Яворов" | F90: основно | G90: Общинско | H90: 125 | I90: 116 | J90: 109 | K90: =+(H90+I90+J90)/3 -> 116.66667 | L90: 150000 | M90: =+L90*0.45 -> 67500 | N90: =+L90*0.45 -> 67500 | O90: =+N90*0.2 -> 13500 | P90: =++L90*0.1 -> 15000 | Q90: 30000 | R90: 3 | S90: =+Q90*0.1 -> 3000 | T90: =+L90+Q90 -> 180000 | U90: =+T90*0.01 -> 1800 | V90: =+T90+U90 -> 181800 | W90: 000011096
A91: 105005 | B91: Благоевград | C91: Белица | D91: Бабяк | E91: Основно училище "Св.св.Кирил и Методий" | F91: основно | G91: Общинско | H91: 121 | I91: 113 | J91: 95 | K91: =+(H91+I91+J91)/3 -> 109.66667 | L91: 150000 | M91: =+L91*0.45 -> 67500 | N91: =+L91*0.45 -> 67500 | O91: =+N91*0.2 -> 13500 | P91: =++L91*0.1 -> 15000 | Q91: 30000 | R91: 3 | S91: =+Q91*0.1 -> 3000 | T91: =+L91+Q91 -> 180000 | U91: =+T91*0.01 -> 1800 | V91: =+T91+U91 -> 181800 | W91: 000012629
A92: 105006 | B92: Благоевград | C92: Белица | D92: Дагоново | E92: Начално училище "Петко Р. Славейков" | F92: начално | G92: Общинско | H92: 30 | I92: 25 | J92: 26 | K92: =+(H92+I92+J92)/3 -> 27 | L92: 50000 | M92: =+L92*0.45 -> 22500 | N92: =+L92*0.45 -> 22500 | O92: =+N92*0.2 -> 4500 | P92: =++L92*0.1 -> 5000 | Q92: 10000 | R92: 1 | S92: =+Q92*0.1 -> 1000 | T92: =+L92+Q92 -> 60000 | U92: =+T92*0.01 -> 600 | V92: =+T92+U92 -> 60600 | W92: 811147205
A93: 105101 | B93: Благоевград | C93: Кресна | D93: Кресна | E93: Средно училище "Св.Паисий Хилендарски" | F93: средно | G93: Общинско | H93: 324 | I93: 341 | J93: 354 | K93: =+(H93+I93+J93)/3 -> 339.66667 | L93: 200000 | M93: =+L93*0.45 -> 90000 | N93: =+L93*0.45 -> 90000 | O93: =+N93*0.2 -> 18000 | P93: =++L93*0.1 -> 20000 | Q93: 50000 | R93: 5 | S93: =+Q93*0.1 -> 5000 | T93: =+L93+Q93 -> 250000 | U93: =+T93*0.01 -> 2500 | V93: =+T93+U93 -> 252500 | W93: 000012789
A94: 105201 | B94: Благоевград | C94: Банско | D94: Банско | E94: Средно училище "Неофит Рилски" | F94: средно | G94: Общинско | H94: 491 | I94: 504 | J94: 566 | K94: =+(H94+I94+J94)/3 -> 520.33333 | L94: =300000 -> 300000 | M94: =+L94*0.45 -> 135000 | N94: =+L94*0.45 -> 135000 | O94: =+N94*0.2 -> 27000 | P94: =++L94*0.1 -> 30000 | Q94: 60000 | R94: 6 | S94: =+Q94*0.1 -> 6000 | T94: =+L94+Q94 -> 360000 | U94: =+T94*0.01 -> 3600 | V94: =+T94+U94 -> 363600 | W94: 000012508
A95: 105202 | B95: Благоевград | C95: Банско | D95: Добринище | E95: Основно училище "Свети Климент Охридски" | F95: основно | G95: Общинско | H95: 138 | I95: 143 | J95: 146 | K95: =+(H95+I95+J95)/3 -> 142.33333 | L95: 150000 | M95: =+L95*0.45 -> 67500 | N95: =+L95*0.45 -> 67500 | O95: =+N95*0.2 -> 13500 | P95: =++L95*0.1 -> 15000 | Q95: 30000 | R95: 3 | S95: =+Q95*0.1 -> 3000 | T95: =+L95+Q95 -> 180000 | U95: =+T95*0.01 -> 1800 | V95: =+T95+U95 -> 181800 | W95: 000012981
A96: 105204 | B96: Благоевград | C96: Банско | D96: Банско | E96: Начално училище "Св. Паисий Хилендарски" | F96: начално | G96: Общинско | H96: 238 | I96: 245 | J96: 260 | K96: =+(H96+I96+J96)/3 -> 247.66667 | L96: 200000 | M96: =+L96*0.45 -> 90000 | N96: =+L96*0.45 -> 90000 | O96: =+N96*0.2 -> 18000 | P96: =++L96*0.1 -> 20000 | Q96: 50000 | R96: 5 | S96: =+Q96*0.1 -> 5000 | T96: =+L96+Q96 -> 250000 | U96: =+T96*0.01 -> 2500 | V96: =+T96+U96 -> 252500 | W96: 000010891
A97: 107020 | B97: Благоевград | C97: Якоруда | D97: Бел камен | E97: Основно училище "Неофит Рилски" | F97: основно | G97: Общинско | H97: 39 | I97: 41 | J97: 36 | K97: =+(H97+I97+J97)/3 -> 38.666667 | L97: 50000 | M97: =+L97*0.45 -> 22500 | N97: =+L97*0.45 -> 22500 | O97: =+N97*0.2 -> 4500 | P97: =++L97*0.1 -> 5000 | Q97: 10000 | R97: 1 | S97: =+Q97*0.1 -> 1000 | T97: =+L97+Q97 -> 60000 | U97: =+T97*0.01 -> 600 | V97: =+T97+U97 -> 60600 | W97: 000013859
A98: 107021 | B98: Благоевград | C98: Якоруда | D98: Смолево | E98: Обединено училище "Гоце Делчев " | F98: обединено | G98: Общинско | H98: 110 | I98: 104 | J98: 107 | K98: =+(H98+I98+J98)/3 -> 107 | L98: 150000 | M98: =+L98*0.45 -> 67500 | N98: =+L98*0.45 -> 67500 | O98: =+N98*0.2 -> 13500 | P98: =++L98*0.1 -> 15000 | Q98: 30000 | R98: 3 | S98: =+Q98*0.1 -> 3000 | T98: =+L98+Q98 -> 180000 | U98: =+T98*0.01 -> 1800 | V98: =+T98+U98 -> 181800 | W98: 000013866
A99: 107090 | B99: Благоевград | C99: Якоруда | D99: Якоруда | E99: Средно училище "Свети Свети Кирил и Методий" | F99: средно | G99: Общинско | H99: 515 | I99: 510 | J99: 510 | K99: =+(H99+I99+J99)/3 -> 511.66667 | L99: =300000*0.7 -> 210000 | M99: =+L99*0.45 -> 94500 | N99: =+L99*0.45 -> 94500 | O99: =+N99*0.2 -> 18900 | P99: =++L99*0.1 -> 21000 | Q99: 60000 | R99: 6 | S99: =+Q99*0.1 -> 6000 | T99: =+L99+Q99 -> 270000 | U99: =+T99*0.01 -> 2700 | V99: =+T99+U99 -> 272700 | W99: 000012611
A100: 107092 | B100: Благоевград | C100: Якоруда | D100: Конарско | E100: Обединено училище "Братя Миладинови" | F100: обединено | G100: Общинско | H100: 144 | I100: 143 | J100: 134 | K100: =+(H100+I100+J100)/3 -> 140.33333 | L100: 150000 | M100: =+L100*0.45 -> 67500 | N100: =+L100*0.45 -> 67500 | O100: =+N100*0.2 -> 13500 | P100: =++L100*0.1 -> 15000 | Q100: 30000 | R100: 3 | S100: =+Q100*0.1 -> 3000 | T100: =+L100+Q100 -> 180000 | U100: =+T100*0.01 -> 1800 | V100: =+T100+U100 -> 181800 | W100: 000013873
...

Sheet Стойности
A1: Училището Ви има ли изграден STEM център към момента на кандидатстване
B2: 1 - Да, 2 - Не
A3: 1.1 | B3: 2
A4: В кой/кои образователни етапи ще се използва центърът
B5: Начален | C5: Гимназиален | D5: Прогимназиален
A6: 1.13 | B6: FALSE | C6: TRUE | D6: TRUE
B7: Декларирам
A8: 5.1 | B8: TRUE
A9: 5.2 | B9: TRUE
